{
  "DailyRankings": [
    {
      "BlogUrl": "/gm84910",
      "Deleted": false,
      "RankDate": "2017-10-04T00:00:00",
      "BlogID": 84910,
      "RankType": 2,
      "Rating": 830,
      "BlogTitle": "(C92) [ONEONE1 (アヘ丸, ぺぽ)] 肉便嬢のカバ○リ其乃惨 (甲鉄城のカバネリ)",
      "BlogThumb": "//static.gmgard.us/Images/thumbs/10311031158242361.jpg",
      "BlogVisit": 10869,
      "PostCount": 99,
      "Author": "古明地恋♥",
      "BlogDate": "2017-10-04T00:30:18.377"
    },
    {
      "BlogUrl": "/gm85012",
      "Deleted": false,
      "RankDate": "2017-10-02T00:00:00",
      "BlogID": 85012,
      "RankType": 2,
      "Rating": 646,
      "BlogTitle": " [170929][アトリエかぐや BARE&BUNNY]しごカレ ~エッチな女子大生とドキ×2ラブレッスン!!",
      "BlogThumb": "//static.gmgard.us/Images/thumbs/12139012004229556.jpg",
      "BlogVisit": 8163,
      "PostCount": 41,
      "Author": "黑色忧郁",
      "BlogDate": "2017-10-01T20:16:34.893"
    },
    {
      "BlogUrl": "/gm85029",
      "Deleted": false,
      "RankDate": "2017-10-02T00:00:00",
      "BlogID": 85029,
      "RankType": 2,
      "Rating": 884,
      "BlogTitle": "[自购][RJ209631][CUTE CATS] ~新人GDoLのあまあま全力ご奉仕っ!~",
      "BlogThumb": "//static.gmgard.us/Images/thumbs/20780301944428454.jpg",
      "BlogVisit": 13839,
      "PostCount": 72,
      "Author": "[资本的力量] 安定",
      "BlogDate": "2017-10-01T20:11:33.72"
    },
    {
      "BlogUrl": "/gm85030",
      "Deleted": false,
      "RankDate": "2017-10-01T00:00:00",
      "BlogID": 85030,
      "RankType": 2,
      "Rating": 1148,
      "BlogTitle": "[無邪気漢化組][綿貫ろん] 明日もきっと想うひと [MJK-17-D660][單行本]",
      "BlogThumb": "//static.gmgard.us/Images/thumbs/13488302008465153.jpg",
      "BlogVisit": 9907,
      "PostCount": 64,
      "Author": "[神经病，凡是女人] x_single_",
      "BlogDate": "2017-09-30T20:08:48.077"
    },
    {
      "BlogUrl": "/gm85031",
      "Deleted": false,
      "RankDate": "2017-10-01T00:00:00",
      "BlogID": 85031,
      "RankType": 2,
      "Rating": 610,
      "BlogTitle": "[無邪気無修宇宙分組][牡丹もちと] トぶが如く (COMIC快楽天ビースト 2017年8月号) [MJK-17-Z725]",
      "BlogThumb": "//static.gmgard.us/Images/thumbs/92178302010291645.jpg",
      "BlogVisit": 5701,
      "PostCount": 23,
      "Author": "[神经病，凡是女人] x_single_",
      "BlogDate": "2017-09-30T20:10:29.507"
    },
    {
      "BlogUrl": "/gm85032",
      "Deleted": false,
      "RankDate": "2017-10-01T00:00:00",
      "BlogID": 85032,
      "RankType": 2,
      "Rating": 523,
      "BlogTitle": "[無邪気無修宇宙分組][愛上陸] アタシに課金してみない?  (コミックゼロス #58)[MJK-17-Z726][無修正]",
      "BlogThumb": "//static.gmgard.us/Images/thumbs/92213302017161828.jpg",
      "BlogVisit": 5786,
      "PostCount": 29,
      "Author": "[神经病，凡是女人] x_single_",
      "BlogDate": "2017-09-30T20:17:16.713"
    },
    {
      "BlogUrl": "/gm85033",
      "Deleted": false,
      "RankDate": "2017-10-01T00:00:00",
      "BlogID": 85033,
      "RankType": 2,
      "Rating": 943,
      "BlogTitle": "[170920][FUNYOURS][DMM.com]マジカルフォーゼプリズムガールR 全CG",
      "BlogThumb": "//static.gmgard.us/Images/thumbs/1990012020372837.jpg",
      "BlogVisit": 9219,
      "PostCount": 54,
      "Author": "樱花抄",
      "BlogDate": "2017-09-30T20:22:05.017"
    },
    {
      "BlogUrl": "/gm85042",
      "Deleted": false,
      "RankDate": "2017-10-01T00:00:00",
      "BlogID": 85042,
      "RankType": 2,
      "Rating": 745,
      "BlogTitle": "[喵萌奶茶屋][170929][ピンクパイナップル]オトメ*ドメイン THE ANIMATION[BIG5_720P 10bit]",
      "BlogThumb": "//static.gmgard.us/Images/thumbs/75560011032303314.jpg",
      "BlogVisit": 18085,
      "PostCount": 86,
      "Author": "[埃罗奈芙老师] 克蕾儿丶艾尔斯坦因",
      "BlogDate": "2017-10-01T00:47:31.523"
    },
    {
      "BlogUrl": "/gm85054",
      "Deleted": false,
      "RankDate": "2017-10-02T00:00:00",
      "BlogID": 85054,
      "RankType": 2,
      "Rating": 989,
      "BlogTitle": "[无毒汉化组] [笹森トモエ] パラダイスファウンド 後編(コミックホットミルク 2017年4月号) [DL版]",
      "BlogThumb": "//static.gmgard.us/Images/thumbs/1744012013224868.jpg",
      "BlogVisit": 9987,
      "PostCount": 47,
      "Author": "whotyour",
      "BlogDate": "2017-10-01T20:13:32.66"
    },
    {
      "BlogUrl": "/gm85064",
      "Deleted": false,
      "RankDate": "2017-10-02T00:00:00",
      "BlogID": 85064,
      "RankType": 2,
      "Rating": 1602,
      "BlogTitle": "[MMD]  R18MMD 小乔的sex (第一人称) (by 自制)",
      "BlogThumb": "//static.gmgard.us/Images/thumbs/85394011826488167.jpg",
      "BlogVisit": 17176,
      "PostCount": 118,
      "Author": "提露密努斯·艾斯特",
      "BlogDate": "2017-10-01T20:16:39.237"
    },
    {
      "BlogUrl": "/gm85080",
      "Deleted": false,
      "RankDate": "2017-10-02T00:00:00",
      "BlogID": 85080,
      "RankType": 2,
      "Rating": 404,
      "BlogTitle": "[lolita研究所汉化][RJ191638][BlueLab]MilkyQuest",
      "BlogThumb": "//static.gmgard.us/Images/thumbs/75125012351333931.jpg",
      "BlogVisit": 10120,
      "PostCount": 57,
      "Author": "玩坏的妖精",
      "BlogDate": "2017-10-01T23:51:33.41"
    },
    {
      "BlogUrl": "/gm85086",
      "Deleted": false,
      "RankDate": "2017-10-04T00:00:00",
      "BlogID": 85086,
      "RankType": 2,
      "Rating": 555,
      "BlogTitle": "[RJ070057][PINK☆DORAGON (染岡ゆすら)] S O N OF A ● E A C H ! (スーパーマリオブラザーズ)",
      "BlogThumb": "//static.gmgard.us/Images/thumbs/37910031141327673.jpg",
      "BlogVisit": 8193,
      "PostCount": 51,
      "Author": "[最远的最近] 老囧",
      "BlogDate": "2017-10-04T00:53:57.47"
    },
    {
      "BlogUrl": "/gm85092",
      "Deleted": false,
      "RankDate": "2017-10-03T00:00:00",
      "BlogID": 85092,
      "RankType": 2,
      "Rating": 1080,
      "BlogTitle": "[RJ201547][survive] 夏色乙女 俺と従姉妹と爛れた性交に耽った夏の思い出(モーションコミック版) ",
      "BlogThumb": "//static.gmgard.us/Images/thumbs/43389022021498802.jpg",
      "BlogVisit": 19122,
      "PostCount": 127,
      "Author": "[斑比酱的眷属] 高阪穗乃果",
      "BlogDate": "2017-10-03T01:11:03.973"
    },
    {
      "BlogUrl": "/gm85093",
      "Deleted": false,
      "RankDate": "2017-10-03T00:00:00",
      "BlogID": 85093,
      "RankType": 2,
      "Rating": 613,
      "BlogTitle": "[谁再提BGF就友尽的朔夜汉化][秋月伊槻] 初めての想い人 ",
      "BlogThumb": "//static.gmgard.us/Images/thumbs/26127022042320024.jpg",
      "BlogVisit": 4530,
      "PostCount": 29,
      "Author": "[半灵庭师] 茔亚",
      "BlogDate": "2017-10-02T20:42:32.44"
    },
    {
      "BlogUrl": "/gm85096",
      "Deleted": false,
      "RankDate": "2017-10-03T00:00:00",
      "BlogID": 85096,
      "RankType": 2,
      "Rating": 710,
      "BlogTitle": "[脸肿字幕组][PoRO]JKとエロコンビニ店長 エロ可愛ママ姉・麻央~痴撮に見惚れるJKフレンズ(度娘)",
      "BlogThumb": "//static.gmgard.us/Images/thumbs/10549022100571859.jpg",
      "BlogVisit": 19887,
      "PostCount": 89,
      "Author": "j瑛里华",
      "BlogDate": "2017-10-03T01:10:36.093"
    },
    {
      "BlogUrl": "/gm85097",
      "Deleted": false,
      "RankDate": "2017-10-03T00:00:00",
      "BlogID": 85097,
      "RankType": 2,
      "Rating": 1197,
      "BlogTitle": "[无毒汉化组](C92) [銀河系PRIDE (B-銀河)] 神威の童貞卒業ウコチャヌプコロ (艦隊これくしょん -艦これ-)",
      "BlogThumb": "//static.gmgard.us/Images/thumbs/81748022103243301.jpg",
      "BlogVisit": 6887,
      "PostCount": 67,
      "Author": "[半灵庭师] 茔亚",
      "BlogDate": "2017-10-02T21:03:24.783"
    },
    {
      "BlogUrl": "/gm85104",
      "Deleted": true,
      "RankDate": "2017-10-03T00:00:00",
      "BlogID": 85104,
      "RankType": 2,
      "Rating": 470,
      "BlogTitle": "[无修正][合集][风来西林汉化][ファーストディストリビューション]淫獣圣战XX  共4篇[1.54G]",
      "BlogThumb": "//static.gmgard.us/Images/thumbs/65579030051126286.jpg",
      "BlogVisit": 13758,
      "PostCount": 0,
      "Author": "大叔来一发吧",
      "BlogDate": "2017-10-03T01:13:56.843"
    },
    {
      "BlogUrl": "/gm85105",
      "Deleted": true,
      "RankDate": "2017-10-05T00:00:00",
      "BlogID": 85105,
      "RankType": 2,
      "Rating": 1854,
      "BlogTitle": "[gfpa个人汉化][170428][ILLUSION] HoneySelect(ハニーセレクト)+大型资料片DLC《ハニーセレクト ~パーティー~》",
      "BlogThumb": "//static.gmgard.us/Images/thumbs/77366040142175486.jpg",
      "BlogVisit": 63485,
      "PostCount": 0,
      "Author": "大叔来一发吧",
      "BlogDate": "2017-10-04T20:33:58.55"
    },
    {
      "BlogUrl": "/gm85115",
      "Deleted": false,
      "RankDate": "2017-10-04T00:00:00",
      "BlogID": 85115,
      "RankType": 2,
      "Rating": 245,
      "BlogTitle": "[黑条汉化][RJ086679][コキュの部屋] ワキ輪姦 (コードギアス, 機動戦士ガンダムSEED, 超昂閃忍ハルカ) ",
      "BlogThumb": "//static.gmgard.us/Images/thumbs/13525031228452205.jpg",
      "BlogVisit": 5354,
      "PostCount": 23,
      "Author": "[最远的最近] 老囧",
      "BlogDate": "2017-10-04T00:57:57.423"
    },
    {
      "BlogUrl": "/gm85118",
      "Deleted": false,
      "RankDate": "2017-10-04T00:00:00",
      "BlogID": 85118,
      "RankType": 2,
      "Rating": 525,
      "BlogTitle": "[MMD]Mantis-X作品合集3[25个/1.42G]",
      "BlogThumb": "//static.gmgard.us/Images/thumbs/17694031426177048.jpg",
      "BlogVisit": 7751,
      "PostCount": 58,
      "Author": "[虹色萝莉薄] OTKSUN",
      "BlogDate": "2017-10-04T01:02:20.47"
    },
    {
      "BlogUrl": "/gm85140",
      "Deleted": false,
      "RankDate": "2017-10-04T00:00:00",
      "BlogID": 85140,
      "RankType": 2,
      "Rating": 275,
      "BlogTitle": " [RJ209051] [まかろんシュガー] とある雨の日の。―少女が快楽に堕ちるまで―",
      "BlogThumb": "//static.gmgard.us/Images/thumbs/18533040332095486.jpg",
      "BlogVisit": 7890,
      "PostCount": 49,
      "Author": "[萝莉] oo789789789",
      "BlogDate": "2017-10-04T03:32:09.61"
    },
    {
      "BlogUrl": "/gm85146",
      "Deleted": false,
      "RankDate": "2017-10-05T00:00:00",
      "BlogID": 85146,
      "RankType": 2,
      "Rating": 1065,
      "BlogTitle": "[生肉][ばにぃうぉ~か~]OVA 妹ビッチに搾られたい #1 妹DE王様ゲーム ~合コンで妹とバッタリで王様ゲームする話~ ",
      "BlogThumb": "//static.gmgard.us/Images/thumbs/10975041619184406.jpg",
      "BlogVisit": 12458,
      "PostCount": 77,
      "Author": "[eden*] ValkyrieMadoka",
      "BlogDate": "2017-10-04T20:40:00.863"
    },
    {
      "BlogUrl": "/gm85149",
      "Deleted": false,
      "RankDate": "2017-10-05T00:00:00",
      "BlogID": 85149,
      "RankType": 2,
      "Rating": 1981,
      "BlogTitle": "[脸肿字幕组][ピンクパイナップル]ばくあね 弟しぼっちゃうぞ! THE ANIMATION ディレクターズカット版",
      "BlogThumb": "//static.gmgard.us/Images/thumbs/63214041738439875.jpg",
      "BlogVisit": 23520,
      "PostCount": 157,
      "Author": "j瑛里华",
      "BlogDate": "2017-10-04T20:36:25.677"
    },
    {
      "BlogUrl": "/gm85159",
      "Deleted": false,
      "RankDate": "2017-10-05T00:00:00",
      "BlogID": 85159,
      "RankType": 2,
      "Rating": 620,
      "BlogTitle": "[MMD]  R18MMD 小乔 DEEP BLUE SONG +18 19 20 23弹(by 咕嘿嘿)",
      "BlogThumb": "//static.gmgard.us/Images/thumbs/16032042200460501.jpg",
      "BlogVisit": 10231,
      "PostCount": 87,
      "Author": "提露密努斯·艾斯特",
      "BlogDate": "2017-10-05T01:41:53.27"
    },
    {
      "BlogUrl": "/gm85164",
      "Deleted": false,
      "RankDate": "2017-10-05T00:00:00",
      "BlogID": 85164,
      "RankType": 2,
      "Rating": 856,
      "BlogTitle": "[闪灵二人组汉化][ゼロの者] あ・パート (コミックジェシカ Vol.3)",
      "BlogThumb": "//static.gmgard.us/Images/thumbs/13039042358353625.jpg",
      "BlogVisit": 9292,
      "PostCount": 74,
      "Author": "[恶魔之妹] 拉媞珐·芙尔兰札",
      "BlogDate": "2017-10-04T23:58:36.02"
    },
    {
      "BlogUrl": "/gm85180",
      "Deleted": false,
      "RankDate": "2017-10-06T00:00:00",
      "BlogID": 85180,
      "RankType": 2,
      "Rating": 1874,
      "BlogTitle": "[final個人漢化](C92) [熟成角砂糖 (sugarBt)] ウルトラビーストなんてなかった2 (ポケットモンスター サン･ムーン)",
      "BlogThumb": "//static.gmgard.us/Images/thumbs/10551052116541590.jpg",
      "BlogVisit": 22412,
      "PostCount": 129,
      "Author": "[最远的最近] 老囧",
      "BlogDate": "2017-10-05T21:18:08.8"
    },
    {
      "BlogUrl": "/gm85188",
      "Deleted": false,
      "RankDate": "2017-10-06T00:00:00",
      "BlogID": 85188,
      "RankType": 2,
      "Rating": 1046,
      "BlogTitle": "[桜都字幕组][ばにぃうぉ~か~]OVA-妹ビッチに搾られたい-#1-妹DE王様ゲーム-~合コンで妹とバッタリで王様ゲームする話~",
      "BlogThumb": "//static.gmgard.us/Images/thumbs/16995052059200809.jpg",
      "BlogVisit": 28393,
      "PostCount": 83,
      "Author": "j瑛里华",
      "BlogDate": "2017-10-05T21:15:16.473"
    },
    {
      "BlogUrl": "/gm85191",
      "Deleted": false,
      "RankDate": "2017-10-06T00:00:00",
      "BlogID": 85191,
      "RankType": 2,
      "Rating": 1100,
      "BlogTitle": "[度娘][合集][脸肿字幕组]2017年9月作品合集X12(2.86G)",
      "BlogThumb": "//static.gmgard.us/Images/thumbs/37890052107566590.jpg",
      "BlogVisit": 13947,
      "PostCount": 88,
      "Author": "j瑛里华",
      "BlogDate": "2017-10-05T21:15:54.427"
    },
    {
      "BlogUrl": "/gm85195",
      "Deleted": false,
      "RankDate": "2017-10-06T00:00:00",
      "BlogID": 85195,
      "RankType": 2,
      "Rating": 923,
      "BlogTitle": "[RJ209965][アオクマシー] まいにちまいと。~妹の麻衣と毎日エッチな生活~",
      "BlogThumb": "//static.gmgard.us/Images/thumbs/17679052224570809.jpg",
      "BlogVisit": 9313,
      "PostCount": 80,
      "Author": "[萝莉] 制杖小春",
      "BlogDate": "2017-10-05T22:24:57.223"
    },
    {
      "BlogUrl": "/gm85201",
      "Deleted": false,
      "RankDate": "2017-10-06T00:00:00",
      "BlogID": 85201,
      "RankType": 2,
      "Rating": 871,
      "BlogTitle": "(C92) [いちごさいず (なつめえり)] みこっとサマー アバンチュール! (Fate/Grand Order)",
      "BlogThumb": "//static.gmgard.us/Images/thumbs/81770052308021903.jpg",
      "BlogVisit": 6675,
      "PostCount": 57,
      "Author": "[王的力量] Mister_Doge",
      "BlogDate": "2017-10-05T23:18:52.127"
    },
    {
      "BlogUrl": "/gm85231",
      "Deleted": false,
      "RankDate": "2017-10-07T00:00:00",
      "BlogID": 85231,
      "RankType": 2,
      "Rating": 513,
      "BlogTitle": "(合集)[幻樱字幕组]裙下有野兽。(R18版)[01-12话][BIG5][1080P][MP4] ",
      "BlogThumb": "//static.gmgard.us/Images/thumbs/66864062101371465.jpg",
      "BlogVisit": 9421,
      "PostCount": 52,
      "Author": "[轮回独断] 漫游火焰",
      "BlogDate": "2017-10-06T21:01:37.38"
    },
    {
      "BlogUrl": "/gm85235",
      "Deleted": false,
      "RankDate": "2017-10-07T00:00:00",
      "BlogID": 85235,
      "RankType": 2,
      "Rating": 3046,
      "BlogTitle": "[桜都字幕组][メリー・ジェーン]キメ恋! 高嶺の華と幼なじみがキマった理由 上巻魔法の薬で恋の成就を(度娘)",
      "BlogThumb": "//static.gmgard.us/Images/thumbs/18158062114547247.jpg",
      "BlogVisit": 46190,
      "PostCount": 278,
      "Author": "[恶魔之妹] 拉媞珐·芙尔兰札",
      "BlogDate": "2017-10-06T21:14:54.773"
    },
    {
      "BlogUrl": "/gm85241",
      "Deleted": false,
      "RankDate": "2017-10-07T00:00:00",
      "BlogID": 85241,
      "RankType": 2,
      "Rating": 729,
      "BlogTitle": "[屏幕髒了漢化] (C92) [RUBBISH選別隊 (無望菜志)] RE25 (Fate/Grand Order)",
      "BlogThumb": "//static.gmgard.us/Images/thumbs/81718062121344122.jpg",
      "BlogVisit": 5208,
      "PostCount": 47,
      "Author": "[半灵庭师] 茔亚",
      "BlogDate": "2017-10-06T21:21:35.773"
    },
    {
      "BlogUrl": "/gm85251",
      "Deleted": false,
      "RankDate": "2017-10-07T00:00:00",
      "BlogID": 85251,
      "RankType": 2,
      "Rating": 370,
      "BlogTitle": "[風的工房][くもえもん] 縄囚犯 ",
      "BlogThumb": "//static.gmgard.us/Images/thumbs/29753062341350684.jpg",
      "BlogVisit": 5407,
      "PostCount": 29,
      "Author": "[原谅她] 地底人",
      "BlogDate": "2017-10-06T23:41:35.163"
    },
    {
      "BlogUrl": "/gm85260",
      "Deleted": false,
      "RankDate": "2017-10-07T00:00:00",
      "BlogID": 85260,
      "RankType": 2,
      "Rating": 1291,
      "BlogTitle": "[脸肿字幕组][171006][メリー・ジェーン] 魂インサート 下巻神様の身体へおじゃまします",
      "BlogThumb": "//static.gmgard.us/Images/thumbs/13190070106111778.jpg",
      "BlogVisit": 23157,
      "PostCount": 184,
      "Author": "[萝莉] 制杖小春",
      "BlogDate": "2017-10-07T01:06:11.287"
    },
    {
      "BlogUrl": "/gm85265",
      "Deleted": false,
      "RankDate": "2017-10-09T00:00:00",
      "BlogID": 85265,
      "RankType": 2,
      "Rating": 338,
      "BlogTitle": "[RJ194178][ポンズラボ] PornFactory",
      "BlogThumb": "//static.gmgard.us/Images/thumbs/19613070335239280.jpg",
      "BlogVisit": 6710,
      "PostCount": 39,
      "Author": "tyuizx",
      "BlogDate": "2017-10-09T01:15:28.65"
    },
    {
      "BlogUrl": "/gm85279",
      "Deleted": false,
      "RankDate": "2017-10-08T00:00:00",
      "BlogID": 85279,
      "RankType": 2,
      "Rating": 425,
      "BlogTitle": "[绅士仓库汉化](C92) [K+W (ささちん)] 初月とムレムレムラムラ夏えっち! (艦隊これくしょん -艦これ-) ",
      "BlogThumb": "//static.gmgard.us/Images/thumbs/64535071501036366.jpg",
      "BlogVisit": 4845,
      "PostCount": 45,
      "Author": "[最远的最近] 老囧",
      "BlogDate": "2017-10-07T23:32:43.297"
    },
    {
      "BlogUrl": "/gm85282",
      "Deleted": false,
      "RankDate": "2017-10-10T00:00:00",
      "BlogID": 85282,
      "RankType": 2,
      "Rating": 538,
      "BlogTitle": "[闪灵二人组汉化][翠野タヌキ]アブナイハナ (COMIC ExE 08) [DL版]",
      "BlogThumb": "//static.gmgard.us/Images/thumbs/13021071518162821.jpg",
      "BlogVisit": 7632,
      "PostCount": 42,
      "Author": "啊哦哦嗯",
      "BlogDate": "2017-10-09T23:20:48.19"
    },
    {
      "BlogUrl": "/gm85287",
      "Deleted": false,
      "RankDate": "2017-10-08T00:00:00",
      "BlogID": 85287,
      "RankType": 2,
      "Rating": 551,
      "BlogTitle": "[自購][RJ208126][ディーゼルマイン]女騎士レティシア[1.61GB]",
      "BlogThumb": "//static.gmgard.us/Images/thumbs/13068072015196093.jpg",
      "BlogVisit": 9006,
      "PostCount": 46,
      "Author": "むちむち小泉花陽",
      "BlogDate": "2017-10-07T22:54:10.14"
    },
    {
      "BlogUrl": "/gm85288",
      "Deleted": false,
      "RankDate": "2017-10-08T00:00:00",
      "BlogID": 85288,
      "RankType": 2,
      "Rating": 383,
      "BlogTitle": "[贝尔西行寺个人汉化][緋乃ひの] 堕ち果てる魔法剣士 (二次元コミックマガジン 器具責め快楽で悶絶絶頂Vol.2) [DL版]",
      "BlogThumb": "//static.gmgard.us/Images/thumbs/18918072032330209.jpg",
      "BlogVisit": 6401,
      "PostCount": 22,
      "Author": "[站长在看着你] 贝尔西行寺",
      "BlogDate": "2017-10-07T20:32:34.13"
    },
    {
      "BlogUrl": "/gm85289",
      "Deleted": false,
      "RankDate": "2017-10-08T00:00:00",
      "BlogID": 85289,
      "RankType": 2,
      "Rating": 560,
      "BlogTitle": "[丧尸汉化] [おるとろ] 肉壺奴隷騎士ベルギア(COMIC アンスリウム 2017年10月号) [DL版]",
      "BlogThumb": "//static.gmgard.us/Images/thumbs/81712072128198549.jpg",
      "BlogVisit": 10714,
      "PostCount": 45,
      "Author": "whotyour",
      "BlogDate": "2017-10-07T22:41:35.313"
    },
    {
      "BlogUrl": "/gm85290",
      "Deleted": false,
      "RankDate": "2017-10-08T00:00:00",
      "BlogID": 85290,
      "RankType": 2,
      "Rating": 1059,
      "BlogTitle": "[RJ186014][MiMiA Cute]フタふたっ(1)~捕らえられた特待生~プレイムービー",
      "BlogThumb": "//static.gmgard.us/Images/thumbs/20958072214152023.jpg",
      "BlogVisit": 16627,
      "PostCount": 108,
      "Author": "[萝莉] 制杖小春",
      "BlogDate": "2017-10-07T22:14:15.703"
    },
    {
      "BlogUrl": "/gm85312",
      "Deleted": false,
      "RankDate": "2017-10-09T00:00:00",
      "BlogID": 85312,
      "RankType": 2,
      "Rating": 575,
      "BlogTitle": "[督不进洞汉化组] (C91) [彩RIP (あやとあやり)] 童貞男子とペアシート",
      "BlogThumb": "//static.gmgard.us/Images/thumbs/13132081441039151.jpg",
      "BlogVisit": 6161,
      "PostCount": 32,
      "Author": "黑吉",
      "BlogDate": "2017-10-08T21:02:26.383"
    },
    {
      "BlogUrl": "/gm85315",
      "Deleted": false,
      "RankDate": "2017-10-09T00:00:00",
      "BlogID": 85315,
      "RankType": 2,
      "Rating": 288,
      "BlogTitle": "[角虫国国都汉化](C92)[SHRINE (人丸)] 幻想生物図鑑 17 (獣死地)",
      "BlogThumb": "//static.gmgard.us/Images/thumbs/13653081630554933.jpg",
      "BlogVisit": 5054,
      "PostCount": 48,
      "Author": "[eden*] 落日羽音",
      "BlogDate": "2017-10-09T00:01:32.76"
    },
    {
      "BlogUrl": "/gm85316",
      "Deleted": false,
      "RankDate": "2017-10-09T00:00:00",
      "BlogID": 85316,
      "RankType": 2,
      "Rating": 496,
      "BlogTitle": "[汉化补丁][141128][Dual Tail]VenusBlood-Hypno汉化补丁",
      "BlogThumb": "//static.gmgard.us/Images/thumbs/11334081641238370.jpg",
      "BlogVisit": 12275,
      "PostCount": 80,
      "Author": "某白痴丶",
      "BlogDate": "2017-10-09T01:23:50.26"
    },
    {
      "BlogUrl": "/gm85320",
      "Deleted": false,
      "RankDate": "2017-10-10T00:00:00",
      "BlogID": 85320,
      "RankType": 2,
      "Rating": 1414,
      "BlogTitle": "[RJ205013] [アトリエわだつみ]チャイナ・インフェルノ Ver.1.5",
      "BlogThumb": "//static.gmgard.us/Images/thumbs/75580082036255557.jpg",
      "BlogVisit": 24260,
      "PostCount": 181,
      "Author": "[lowb] 懼魇",
      "BlogDate": "2017-10-10T00:18:12.713"
    },
    {
      "BlogUrl": "/gm85321",
      "Deleted": false,
      "RankDate": "2017-10-10T00:00:00",
      "BlogID": 85321,
      "RankType": 2,
      "Rating": 1719,
      "BlogTitle": "[桜都字幕组][BOOTLEG]さきゅばみすと・すとーりー ~のんひゅーまあんらいふ~ THE ANIMATION(度娘)",
      "BlogThumb": "//static.gmgard.us/Images/thumbs/20018101929069675.jpg",
      "BlogVisit": 31331,
      "PostCount": 174,
      "Author": "j瑛里华",
      "BlogDate": "2017-10-09T22:04:04.12"
    },
    {
      "BlogUrl": "/gm85323",
      "Deleted": false,
      "RankDate": "2017-10-09T00:00:00",
      "BlogID": 85323,
      "RankType": 2,
      "Rating": 1031,
      "BlogTitle": "[萝莉援助汉化组] (C92) [RIN (モチ)] 純血のデヴァイス",
      "BlogThumb": "//static.gmgard.us/Images/thumbs/60551082348408995.jpg",
      "BlogVisit": 10601,
      "PostCount": 105,
      "Author": "Concord_e",
      "BlogDate": "2017-10-08T23:48:45.087"
    },
    {
      "BlogUrl": "/gm85335",
      "Deleted": false,
      "RankDate": "2017-10-10T00:00:00",
      "BlogID": 85335,
      "RankType": 2,
      "Rating": 725,
      "BlogTitle": "[新视界中文版] [Noise] お兄ちゃんそんなにショートパンツ好きなの",
      "BlogThumb": "//static.gmgard.us/Images/thumbs/15244091903327989.jpg",
      "BlogVisit": 7310,
      "PostCount": 64,
      "Author": "[彩虹Project] 跳绳怪",
      "BlogDate": "2017-10-10T00:17:57.623"
    },
    {
      "BlogUrl": "/gm85336",
      "Deleted": false,
      "RankDate": "2017-10-12T00:00:00",
      "BlogID": 85336,
      "RankType": 2,
      "Rating": 1245,
      "BlogTitle": "[鲤家汉化] (同人CG集) [RJ115009][ひぐま屋] もしも近所にHなサービスをしてくれる銭湯があったら",
      "BlogThumb": "//static.gmgard.us/Images/thumbs/98795091947412926.jpg",
      "BlogVisit": 9031,
      "PostCount": 85,
      "Author": "TōgōNaoya",
      "BlogDate": "2017-10-11T21:22:37.137"
    },
    {
      "BlogUrl": "/gm85338",
      "Deleted": false,
      "RankDate": "2017-10-10T00:00:00",
      "BlogID": 85338,
      "RankType": 2,
      "Rating": 1430,
      "BlogTitle": "[RJ162718][FreakilyCharming] 奴隷との生活 -Teaching Feeling-Ver.2.0.β-a",
      "BlogThumb": "//static.gmgard.us/Images/thumbs/1563092039382914.jpg",
      "BlogVisit": 14272,
      "PostCount": 180,
      "Author": "[魔理沙的后宫] xianhong",
      "BlogDate": "2017-10-09T23:35:23.387"
    },
    {
      "BlogUrl": "/gm85352",
      "Deleted": false,
      "RankDate": "2017-10-12T00:00:00",
      "BlogID": 85352,
      "RankType": 2,
      "Rating": 1036,
      "BlogTitle": "(全彩)[25cup个人汉化][Ramjak] Atonement Camp Ch.0-53 ",
      "BlogThumb": "//static.gmgard.us/Images/thumbs/94927101651397019.jpg",
      "BlogVisit": 11545,
      "PostCount": 93,
      "Author": "錵錵",
      "BlogDate": "2017-10-11T22:19:36.563"
    },
    {
      "BlogUrl": "/gm85357",
      "Deleted": false,
      "RankDate": "2017-10-11T00:00:00",
      "BlogID": 85357,
      "RankType": 2,
      "Rating": 538,
      "BlogTitle": "[风车字幕组]名侦探柯南:殷红的恋歌[剧场版][BDrip][GB&BIG5][720P&1080P][MP4] ",
      "BlogThumb": "//static.gmgard.us/Images/thumbs/11682102004399207.jpg",
      "BlogVisit": 7045,
      "PostCount": 70,
      "Author": "[轮回独断] 漫游火焰",
      "BlogDate": "2017-10-10T20:04:40.267"
    },
    {
      "BlogUrl": "/gm85359",
      "Deleted": false,
      "RankDate": "2017-10-11T00:00:00",
      "BlogID": 85359,
      "RankType": 2,
      "Rating": 405,
      "BlogTitle": "[開坑當做例行重嵌組-掃圖分部][月野定規] 艶色情話",
      "BlogThumb": "//static.gmgard.us/Images/thumbs/80272102042257489.jpg",
      "BlogVisit": 4567,
      "PostCount": 32,
      "Author": "[原谅她] 地底人",
      "BlogDate": "2017-10-10T20:42:25.843"
    },
    {
      "BlogUrl": "/gm85364",
      "Deleted": false,
      "RankDate": "2017-10-11T00:00:00",
      "BlogID": 85364,
      "RankType": 2,
      "Rating": 955,
      "BlogTitle": "[開坑當做例行重嵌組-掃圖分部][アーセナル] 恋膣穴",
      "BlogThumb": "//static.gmgard.us/Images/thumbs/80234102057011707.jpg",
      "BlogVisit": 9986,
      "PostCount": 81,
      "Author": "[原谅她] 地底人",
      "BlogDate": "2017-10-10T20:57:01.267"
    },
    {
      "BlogUrl": "/gm85366",
      "Deleted": false,
      "RankDate": "2017-10-11T00:00:00",
      "BlogID": 85366,
      "RankType": 2,
      "Rating": 355,
      "BlogTitle": "[無邪気漢化組][ぶんぼん] 触手退治は快楽の始まり (正義のヒロイン姦獄ファイルVol.16) [MJK-17-Z733]",
      "BlogThumb": "//static.gmgard.us/Images/thumbs/18216110053497488.jpg",
      "BlogVisit": 5736,
      "PostCount": 24,
      "Author": "[神经病，凡是女人] x_single_",
      "BlogDate": "2017-10-11T00:53:50.14"
    },
    {
      "BlogUrl": "/gm85367",
      "Deleted": false,
      "RankDate": "2017-10-11T00:00:00",
      "BlogID": 85367,
      "RankType": 2,
      "Rating": 418,
      "BlogTitle": "[無邪気無修宇宙分組][一ノ瀬ランド] ふつうの・オンナノコ (COMIC快楽天ビースト 2017年4月号) [MJK-17-Z737]",
      "BlogThumb": "//static.gmgard.us/Images/thumbs/16976110056435300.jpg",
      "BlogVisit": 5184,
      "PostCount": 69,
      "Author": "[神经病，凡是女人] x_single_",
      "BlogDate": "2017-10-11T00:56:44.06"
    },
    {
      "BlogUrl": "/gm85375",
      "Deleted": false,
      "RankDate": "2017-10-12T00:00:00",
      "BlogID": 85375,
      "RankType": 2,
      "Rating": 230,
      "BlogTitle": "[RJ203027](同人音声)[B-bishop]搾精無言少女のフェラチオフルコース 肉棒を捧げて敗北するゲーム フェラCG&水音Voice",
      "BlogThumb": "//static.gmgard.us/Images/thumbs/17874111854581149.jpg",
      "BlogVisit": 4214,
      "PostCount": 18,
      "Author": "[欧洲人] hermetic",
      "BlogDate": "2017-10-11T22:25:57.803"
    },
    {
      "BlogUrl": "/gm85377",
      "Deleted": false,
      "RankDate": "2017-10-13T00:00:00",
      "BlogID": 85377,
      "RankType": 2,
      "Rating": 350,
      "BlogTitle": "[RJ210101][ひぐま屋 (野良ヒグマ)] おっぱいを触らせてくれる家庭教師のおねえさんの話",
      "BlogThumb": "//static.gmgard.us/Images/thumbs/19938121806296365.jpg",
      "BlogVisit": 3872,
      "PostCount": 25,
      "Author": "[欧洲人] hermetic",
      "BlogDate": "2017-10-12T20:34:02.967"
    },
    {
      "BlogUrl": "/gm85378",
      "Deleted": false,
      "RankDate": "2017-10-12T00:00:00",
      "BlogID": 85378,
      "RankType": 2,
      "Rating": 791,
      "BlogTitle": "(C91) [SLeeVe (Sody)] ちっちゃいこの本 Vol.8",
      "BlogThumb": "//static.gmgard.us/Images/thumbs/17380112228155623.jpg",
      "BlogVisit": 6689,
      "PostCount": 74,
      "Author": "[迷影重重] 蓝白条纹胖次",
      "BlogDate": "2017-10-11T22:30:40.383"
    },
    {
      "BlogUrl": "/gm85384",
      "Deleted": false,
      "RankDate": "2017-10-13T00:00:00",
      "BlogID": 85384,
      "RankType": 2,
      "Rating": 675,
      "BlogTitle": "[RJ208260][我が家の黒歴史]ツインクワイエット-深層洗脳 歪められた正義-",
      "BlogThumb": "//static.gmgard.us/Images/thumbs/82062122023358864.jpg",
      "BlogVisit": 11085,
      "PostCount": 47,
      "Author": "[eden*] 茕兔丶",
      "BlogDate": "2017-10-12T20:32:57.323"
    },
    {
      "BlogUrl": "/gm85386",
      "Deleted": false,
      "RankDate": "2017-10-12T00:00:00",
      "BlogID": 85386,
      "RankType": 2,
      "Rating": 420,
      "BlogTitle": "[MMD]踊り子(by  いちいちに  )",
      "BlogThumb": "//static.gmgard.us/Images/thumbs/10850121414357458.jpg",
      "BlogVisit": 15522,
      "PostCount": 137,
      "Author": "[Blessing Software] 云姬",
      "BlogDate": "2017-10-12T14:14:36.417"
    },
    {
      "BlogUrl": "/gm85394",
      "Deleted": false,
      "RankDate": "2017-10-13T00:00:00",
      "BlogID": 85394,
      "RankType": 2,
      "Rating": 1586,
      "BlogTitle": "[無邪気無修宇宙分組][智弘カイ] 連休の過ごし方 (COMIC快楽天ビースト 2017年8月号) [MJK-17-Z736]",
      "BlogThumb": "//static.gmgard.us/Images/thumbs/44536122036578708.jpg",
      "BlogVisit": 9959,
      "PostCount": 84,
      "Author": "[神经病，凡是女人] x_single_",
      "BlogDate": "2017-10-12T20:36:58.34"
    },
    {
      "BlogUrl": "/gm85396",
      "Deleted": false,
      "RankDate": "2017-10-14T00:00:00",
      "BlogID": 85396,
      "RankType": 2,
      "Rating": 445,
      "BlogTitle": "[合集][システム4-5-1] 16作Flash游戏合集",
      "BlogThumb": "//static.gmgard.us/Images/thumbs/94853122159437614.jpg",
      "BlogVisit": 5589,
      "PostCount": 54,
      "Author": "[欧洲人] hermetic",
      "BlogDate": "2017-10-13T20:29:19.82"
    },
    {
      "BlogUrl": "/gm85398",
      "Deleted": false,
      "RankDate": "2017-10-14T00:00:00",
      "BlogID": 85398,
      "RankType": 2,
      "Rating": 657,
      "BlogTitle": "[RJ071234] [Violation] つっぱりドットシミュレーター",
      "BlogThumb": "//static.gmgard.us/Images/thumbs/18126122251031052.jpg",
      "BlogVisit": 8128,
      "PostCount": 54,
      "Author": "[欧洲人] hermetic",
      "BlogDate": "2017-10-13T20:24:47.85"
    },
    {
      "BlogUrl": "/gm85399",
      "Deleted": false,
      "RankDate": "2017-10-13T00:00:00",
      "BlogID": 85399,
      "RankType": 2,
      "Rating": 435,
      "BlogTitle": "[無邪気無修宇宙分組][utu] 大家さんのか・お・り (COMIC失楽天 2017年9月号) [MJK-17-Z735]",
      "BlogThumb": "//static.gmgard.us/Images/thumbs/44611130035422302.jpg",
      "BlogVisit": 5962,
      "PostCount": 41,
      "Author": "[神经病，凡是女人] x_single_",
      "BlogDate": "2017-10-13T00:35:43.543"
    },
    {
      "BlogUrl": "/gm85400",
      "Deleted": false,
      "RankDate": "2017-10-13T00:00:00",
      "BlogID": 85400,
      "RankType": 2,
      "Rating": 515,
      "BlogTitle": "[RJ202702][ニート(株)] 動画これくしょん -島風-",
      "BlogThumb": "//static.gmgard.us/Images/thumbs/11193130121517927.jpg",
      "BlogVisit": 10593,
      "PostCount": 110,
      "Author": "[萝莉] 制杖小春",
      "BlogDate": "2017-10-13T01:21:51.887"
    },
    {
      "BlogUrl": "/gm85403",
      "Deleted": false,
      "RankDate": "2017-10-14T00:00:00",
      "BlogID": 85403,
      "RankType": 2,
      "Rating": 1120,
      "BlogTitle": "[附ZOD界面汉化补丁][171013][ILLUSION]プレイホーム(PLAY HOME)(购入特典&预约特典附)",
      "BlogThumb": "//static.gmgard.us/Images/thumbs/18040131226453239.jpg",
      "BlogVisit": 62141,
      "PostCount": 474,
      "Author": "[欧洲人] ziz",
      "BlogDate": "2017-10-14T09:52:45.273"
    },
    {
      "BlogUrl": "/gm85409",
      "Deleted": false,
      "RankDate": "2017-10-14T00:00:00",
      "BlogID": 85409,
      "RankType": 2,
      "Rating": 1380,
      "BlogTitle": "[驭灵师个人汉化][魂神]一夜の魔法(コミックアンリアル 2016年10月号 Vol.63)",
      "BlogThumb": "//static.gmgard.us/Images/thumbs/10671131916214912.jpg",
      "BlogVisit": 9681,
      "PostCount": 84,
      "Author": "驭灵师",
      "BlogDate": "2017-10-13T20:24:31.193"
    },
    {
      "BlogUrl": "/gm85418",
      "Deleted": false,
      "RankDate": "2017-10-14T00:00:00",
      "BlogID": 85418,
      "RankType": 2,
      "Rating": 371,
      "BlogTitle": "[風的工房] [タカスギコウ] けつえん熟女 血緣近親熟女 ",
      "BlogThumb": "//static.gmgard.us/Images/thumbs/29743140047080225.jpg",
      "BlogVisit": 6697,
      "PostCount": 46,
      "Author": "[原谅她] 地底人",
      "BlogDate": "2017-10-14T00:47:08.133"
    },
    {
      "BlogUrl": "/gm85438",
      "Deleted": false,
      "RankDate": "2017-10-15T00:00:00",
      "BlogID": 85438,
      "RankType": 2,
      "Rating": 310,
      "BlogTitle": "(转载)让你见识下什么叫真正的中华料理,《中华小当家》续作漫画 11 月开始连载",
      "BlogThumb": "http://ww1.sinaimg.cn/large/d63ab74bly1fkhmhwmefdj20dw0a5diz.jpg",
      "BlogVisit": 3153,
      "PostCount": 53,
      "Author": "[轮回独断] 漫游火焰",
      "BlogDate": "2017-10-14T21:58:49.39"
    },
    {
      "BlogUrl": "/gm85439",
      "Deleted": false,
      "RankDate": "2017-10-15T00:00:00",
      "BlogID": 85439,
      "RankType": 2,
      "Rating": 684,
      "BlogTitle": "[全彩](合集)[海贼圈制作][尾田荣一郎]ONE PIECE/海贼王[01-61卷] ",
      "BlogThumb": "//static.gmgard.us/Images/thumbs/14975142221158426.jpg",
      "BlogVisit": 7940,
      "PostCount": 68,
      "Author": "[轮回独断] 漫游火焰",
      "BlogDate": "2017-10-14T22:21:18.217"
    },
    {
      "BlogUrl": "/gm85442",
      "Deleted": false,
      "RankDate": "2017-10-16T00:00:00",
      "BlogID": 85442,
      "RankType": 2,
      "Rating": 210,
      "BlogTitle": "[P站ID=480901][団栗] 戦士♀のアンケート冒険1~16",
      "BlogThumb": "//static.gmgard.us/Images/thumbs/20432152254514013.jpg",
      "BlogVisit": 6092,
      "PostCount": 39,
      "Author": "忍不住呻吟的妹子",
      "BlogDate": "2017-10-16T16:37:30.427"
    },
    {
      "BlogUrl": "/gm85446",
      "Deleted": false,
      "RankDate": "2017-10-15T00:00:00",
      "BlogID": 85446,
      "RankType": 2,
      "Rating": 545,
      "BlogTitle": "[萝莉援助汉化组] [エロマズン (まー九郎)] ロリうどんげのHな災難 (東方Project) [DL版]",
      "BlogThumb": "//static.gmgard.us/Images/thumbs/14724150957341864.jpg",
      "BlogVisit": 7879,
      "PostCount": 97,
      "Author": "Concord_e",
      "BlogDate": "2017-10-15T09:57:34.703"
    },
    {
      "BlogUrl": "/gm85448",
      "Deleted": false,
      "RankDate": "2017-10-15T00:00:00",
      "BlogID": 85448,
      "RankType": 2,
      "Rating": 135,
      "BlogTitle": "[新视界中文版] [ピジャ]  ねぇ、…しよ♥",
      "BlogThumb": "//static.gmgard.us/Images/thumbs/81767151128406395.jpg",
      "BlogVisit": 21276,
      "PostCount": 146,
      "Author": "[彩虹Project] 跳绳怪",
      "BlogDate": "2017-10-15T18:24:08.783"
    },
    {
      "BlogUrl": "/gm85453",
      "Deleted": false,
      "RankDate": "2017-10-15T00:00:00",
      "BlogID": 85453,
      "RankType": 2,
      "Rating": 120,
      "BlogTitle": "[RJ209025](同人音声)[ristorante]夢魔のお宿",
      "BlogThumb": "//static.gmgard.us/Images/thumbs/17291151529082671.jpg",
      "BlogVisit": 2883,
      "PostCount": 21,
      "Author": "[唱歌好听] 冰缘吻雪",
      "BlogDate": "2017-10-15T15:29:08.47"
    },
    {
      "BlogUrl": "/gm85460",
      "Deleted": false,
      "RankDate": "2017-10-16T00:00:00",
      "BlogID": 85460,
      "RankType": 2,
      "Rating": 850,
      "BlogTitle": "[4K掃圖組] [さいもん] 異世界の魔法使い",
      "BlogThumb": "//static.gmgard.us/Images/thumbs/20883152341186982.jpg",
      "BlogVisit": 20254,
      "PostCount": 181,
      "Author": "[彩虹Project] 跳绳怪",
      "BlogDate": "2017-10-16T16:38:02.74"
    },
    {
      "BlogUrl": "/gm85462",
      "Deleted": false,
      "RankDate": "2017-10-17T00:00:00",
      "BlogID": 85462,
      "RankType": 2,
      "Rating": 215,
      "BlogTitle": "[日翻河马(贴吧汉化)](一般小说)[镰池和马]新約·とある魔術の禁書目録(17)(EPUB+TXT)",
      "BlogThumb": "//static.gmgard.us/Images/thumbs/19720152350013388.jpg",
      "BlogVisit": 2277,
      "PostCount": 21,
      "Author": "[真相的探求者] 不质之症",
      "BlogDate": "2017-10-17T00:09:16.61"
    },
    {
      "BlogUrl": "/gm85464",
      "Deleted": false,
      "RankDate": "2017-10-16T00:00:00",
      "BlogID": 85464,
      "RankType": 2,
      "Rating": 1195,
      "BlogTitle": "[萝莉援助汉化组] [田辺京] プち妻おもちゃ箱 (LQ -Little Queen- vol.16) [DL版]",
      "BlogThumb": "//static.gmgard.us/Images/thumbs/73671160013104171.jpg",
      "BlogVisit": 11077,
      "PostCount": 111,
      "Author": "Concord_e",
      "BlogDate": "2017-10-16T00:13:10.777"
    },
    {
      "BlogUrl": "/gm85466",
      "Deleted": false,
      "RankDate": "2017-10-16T00:00:00",
      "BlogID": 85466,
      "RankType": 2,
      "Rating": 180,
      "BlogTitle": "[提取动画][RJ200500] [NEKO WORKs] ネコぱら vol.3 ネコたちのアロマティゼ",
      "BlogThumb": "//static.gmgard.us/Images/thumbs/76882161245094327.jpg",
      "BlogVisit": 9809,
      "PostCount": 99,
      "Author": "[王的力量] 在原_七海",
      "BlogDate": "2017-10-16T12:23:51.37"
    },
    {
      "BlogUrl": "/gm85467",
      "Deleted": true,
      "RankDate": "2017-10-16T00:00:00",
      "BlogID": 85467,
      "RankType": 2,
      "Rating": 190,
      "BlogTitle": "[RJ203762][トカゲ森]リアラと魔物の村",
      "BlogThumb": "//static.gmgard.us/Images/thumbs/15393161249364795.jpg",
      "BlogVisit": 4493,
      "PostCount": 0,
      "Author": "[恶魔之妹] 孤单夜行",
      "BlogDate": "2017-10-16T16:44:16.523"
    },
    {
      "BlogUrl": "/gm85473",
      "Deleted": false,
      "RankDate": "2017-10-17T00:00:00",
      "BlogID": 85473,
      "RankType": 2,
      "Rating": 485,
      "BlogTitle": "uTorrent.v2.21-----代替渣雷的小道具",
      "BlogThumb": "//static.gmgard.us/Images/thumbs/72252161019572455.jpg",
      "BlogVisit": 13523,
      "PostCount": 218,
      "Author": "[欧洲人] 黒翼凤尾蝶",
      "BlogDate": "2017-10-17T13:44:26.313"
    },
    {
      "BlogUrl": "/gm85476",
      "Deleted": false,
      "RankDate": "2017-10-18T00:00:00",
      "BlogID": 85476,
      "RankType": 2,
      "Rating": 1652,
      "BlogTitle": "[汉化硬盘版][脸肿汉化组][160527] [Frill] 清楚で真面目な彼女が、最凶ヤリサーに勧誘されたら…?(附全CG存档)",
      "BlogThumb": "//static.gmgard.us/Images/thumbs/66292172206325644.jpg",
      "BlogVisit": 18002,
      "PostCount": 159,
      "Author": "rapt1993",
      "BlogDate": "2017-10-17T22:05:40.627"
    },
    {
      "BlogUrl": "/gm85477",
      "Deleted": true,
      "RankDate": "2017-10-17T00:00:00",
      "BlogID": 85477,
      "RankType": 2,
      "Rating": 1107,
      "BlogTitle": "[魔穗字幕组][ピンクパイナップル]欲情バズーカ THE ANIMATION 「たっぷり濃いのイッパツで!」",
      "BlogThumb": "//static.gmgard.us/Images/thumbs/1387162354369067.jpg",
      "BlogVisit": 17369,
      "PostCount": 0,
      "Author": "[教科书般的黑丝] 帮我关下灯，谢谢",
      "BlogDate": "2017-10-17T00:06:56.923"
    },
    {
      "BlogUrl": "/gm85478",
      "Deleted": false,
      "RankDate": "2017-10-18T00:00:00",
      "BlogID": 85478,
      "RankType": 2,
      "Rating": 246,
      "BlogTitle": "(转载)各位,准备好来ps4上氪vr版“扶她苟”(《Fate/Grand Order》)了么",
      "BlogThumb": "//static.gmgard.us/Images/thumbs/16369170005455317.jpg",
      "BlogVisit": 4919,
      "PostCount": 27,
      "Author": "[欧洲人] 黒翼凤尾蝶",
      "BlogDate": "2017-10-17T20:21:13.14"
    },
    {
      "BlogUrl": "/gm85480",
      "Deleted": false,
      "RankDate": "2017-10-17T00:00:00",
      "BlogID": 85480,
      "RankType": 2,
      "Rating": 626,
      "BlogTitle": "[風的工房] [猫多にぐら] 彼女は野外露出系ヘンタイ 戶外戳插! ",
      "BlogThumb": "//static.gmgard.us/Images/thumbs/29758170033148911.jpg",
      "BlogVisit": 9232,
      "PostCount": 83,
      "Author": "[原谅她] 地底人",
      "BlogDate": "2017-10-17T00:33:14.987"
    },
    {
      "BlogUrl": "/gm85482",
      "Deleted": false,
      "RankDate": "2017-10-19T00:00:00",
      "BlogID": 85482,
      "RankType": 2,
      "Rating": 490,
      "BlogTitle": "[补档][新视界中文版][MMScan][ゼロの者] シス☆ブラっ 第2卷",
      "BlogThumb": "//static.gmgard.us/Images/thumbs/81713170313159848.jpg",
      "BlogVisit": 5200,
      "PostCount": 32,
      "Author": "[七曜的大法师] jackie9807",
      "BlogDate": "2017-10-18T20:59:13.143"
    },
    {
      "BlogUrl": "/gm85484",
      "Deleted": false,
      "RankDate": "2017-10-17T00:00:00",
      "BlogID": 85484,
      "RankType": 2,
      "Rating": 90,
      "BlogTitle": "[RJ205901](同人音声)[ねむりぬこ][耳かき・耳舐め]四季のまほろば庵・涼夏・弐[バイノーラル・ハイレゾ]",
      "BlogThumb": "//static.gmgard.us/Images/thumbs/20935171042143911.jpg",
      "BlogVisit": 2192,
      "PostCount": 21,
      "Author": "[唱歌好听] 冰缘吻雪",
      "BlogDate": "2017-10-17T10:42:14.487"
    },
    {
      "BlogUrl": "/gm85487",
      "Deleted": false,
      "RankDate": "2017-10-18T00:00:00",
      "BlogID": 85487,
      "RankType": 2,
      "Rating": 553,
      "BlogTitle": "[MMD] 江風でGirls / 0点以下ならお仕置き2/4(by Enomotto)",
      "BlogThumb": "//static.gmgard.us/Images/thumbs/30688171352257817.jpg",
      "BlogVisit": 6323,
      "PostCount": 41,
      "Author": "[轮回独断] Mogan",
      "BlogDate": "2017-10-17T22:01:46.253"
    },
    {
      "BlogUrl": "/gm85489",
      "Deleted": true,
      "RankDate": "2017-10-18T00:00:00",
      "BlogID": 85489,
      "RankType": 2,
      "Rating": 630,
      "BlogTitle": "[RJ208776][ランドカット]ミーアのお仕事",
      "BlogThumb": "//static.gmgard.us/Images/thumbs/10925171646432661.jpg",
      "BlogVisit": 7813,
      "PostCount": 0,
      "Author": "[恶魔之妹] 孤单夜行",
      "BlogDate": "2017-10-17T22:03:20.69"
    },
    {
      "BlogUrl": "/gm85498",
      "Deleted": false,
      "RankDate": "2017-10-18T00:00:00",
      "BlogID": 85498,
      "RankType": 2,
      "Rating": 385,
      "BlogTitle": "[脸肿汉化组][RJ202510][さーくるくらすけ倉庫]フランと罪人の島 (芙兰与罪人之岛 ver1.00)",
      "BlogThumb": "//static.gmgard.us/Images/thumbs/10154181328088301.jpg",
      "BlogVisit": 13156,
      "PostCount": 182,
      "Author": "[萝莉] 制杖小春",
      "BlogDate": "2017-10-18T13:28:08.877"
    },
    {
      "BlogUrl": "/gm85500",
      "Deleted": false,
      "RankDate": "2017-10-19T00:00:00",
      "BlogID": 85500,
      "RankType": 2,
      "Rating": 840,
      "BlogTitle": "[自购][RJ206082][H.H.WORKS]FlashCycling~自転車露出主義~[フリーライドろしゅつRPG]",
      "BlogThumb": "//static.gmgard.us/Images/thumbs/14011181537376426.jpg",
      "BlogVisit": 9298,
      "PostCount": 64,
      "Author": "しばけん",
      "BlogDate": "2017-10-18T21:02:16.61"
    },
    {
      "BlogUrl": "/gm85506",
      "Deleted": false,
      "RankDate": "2017-10-20T00:00:00",
      "BlogID": 85506,
      "RankType": 2,
      "Rating": 776,
      "BlogTitle": "[最果ての神狐字幕组][ガールズトーク]淫夢学園 「淫夢に囚われた美人姉妹」",
      "BlogThumb": "//static.gmgard.us/Images/thumbs/19812181954104707.jpg",
      "BlogVisit": 10982,
      "PostCount": 77,
      "Author": "[lowb] 虎牙伤丁",
      "BlogDate": "2017-10-19T20:30:28.777"
    },
    {
      "BlogUrl": "/gm85509",
      "Deleted": false,
      "RankDate": "2017-10-19T00:00:00",
      "BlogID": 85509,
      "RankType": 2,
      "Rating": 1065,
      "BlogTitle": "[風的工房][ててるん] むちむちどびゅぅ! 軟嫩軟嫩噗咻咻?  ",
      "BlogThumb": "//static.gmgard.us/Images/thumbs/29743182117323770.jpg",
      "BlogVisit": 7684,
      "PostCount": 88,
      "Author": "[原谅她] 地底人",
      "BlogDate": "2017-10-18T21:17:32.503"
    },
    {
      "BlogUrl": "/gm85512",
      "Deleted": false,
      "RankDate": "2017-10-19T00:00:00",
      "BlogID": 85512,
      "RankType": 2,
      "Rating": 656,
      "BlogTitle": " [无毒汉化组](C92) [USAGIBOSU (くろわ)] DEEP d'ARC FANTASY (Fate/Grand Order)",
      "BlogThumb": "//static.gmgard.us/Images/thumbs/51523190119419111.jpg",
      "BlogVisit": 13415,
      "PostCount": 179,
      "Author": "[好朋友] 绅士的我33",
      "BlogDate": "2017-10-19T11:46:39.747"
    },
    {
      "BlogUrl": "/gm85514",
      "Deleted": false,
      "RankDate": "2017-10-20T00:00:00",
      "BlogID": 85514,
      "RankType": 2,
      "Rating": 1881,
      "BlogTitle": "[闪灵二人组汉化][ホムンクルス] 恋ひ結び奇譚(COMlC 快楽天 2017年11月号) [DL版]",
      "BlogThumb": "//static.gmgard.us/Images/thumbs/14648190656033077.jpg",
      "BlogVisit": 10667,
      "PostCount": 125,
      "Author": "美堂蛮",
      "BlogDate": "2017-10-19T21:02:38.793"
    },
    {
      "BlogUrl": "/gm85521",
      "Deleted": true,
      "RankDate": "2017-10-20T00:00:00",
      "BlogID": 85521,
      "RankType": 2,
      "Rating": 779,
      "BlogTitle": "[RJ210220][オドントティラヌス] 若妻スフレ",
      "BlogThumb": "//static.gmgard.us/Images/thumbs/13064192024436828.jpg",
      "BlogVisit": 8535,
      "PostCount": 0,
      "Author": "[恶魔之妹] 孤单夜行",
      "BlogDate": "2017-10-19T21:02:52.887"
    },
    {
      "BlogUrl": "/gm85524",
      "Deleted": false,
      "RankDate": "2017-10-20T00:00:00",
      "BlogID": 85524,
      "RankType": 2,
      "Rating": 863,
      "BlogTitle": "[開坑當做例行重嵌組-掃圖分部][天乃一水] 聖堕陰陽―聖女の貌した淫蕩",
      "BlogThumb": "//static.gmgard.us/Images/thumbs/80295192153251828.jpg",
      "BlogVisit": 8698,
      "PostCount": 51,
      "Author": "[原谅她] 地底人",
      "BlogDate": "2017-10-19T21:53:25.293"
    },
    {
      "BlogUrl": "/gm85525",
      "Deleted": false,
      "RankDate": "2017-10-20T00:00:00",
      "BlogID": 85525,
      "RankType": 2,
      "Rating": 685,
      "BlogTitle": "[171020][GOLD BEAR]龍堂寺士門の淫謀 前編 性奴隷調教+特典",
      "BlogThumb": "//static.gmgard.us/Images/thumbs/91543200214205562.jpg",
      "BlogVisit": 14682,
      "PostCount": 149,
      "Author": "[萝莉] 制杖小春",
      "BlogDate": "2017-10-20T02:14:20.9"
    },
    {
      "BlogUrl": "/gm85526",
      "Deleted": false,
      "RankDate": "2017-10-21T00:00:00",
      "BlogID": 85526,
      "RankType": 2,
      "Rating": 1083,
      "BlogTitle": "[生肉](全彩)(COMIC1☆12) [OrangeMaru (YD)] 自動攻略 (Fate/Grand Order)",
      "BlogThumb": "//static.gmgard.us/Images/thumbs/81728200334022437.jpg",
      "BlogVisit": 8164,
      "PostCount": 91,
      "Author": "[十七岁的妖怪贤者] 八云煌",
      "BlogDate": "2017-10-20T22:17:30.903"
    },
    {
      "BlogUrl": "/gm85546",
      "Deleted": false,
      "RankDate": "2017-10-21T00:00:00",
      "BlogID": 85546,
      "RankType": 2,
      "Rating": 251,
      "BlogTitle": "(合集)[OPFans枫雪动漫字幕组]ONE PIECE/海贼王 剧场版全集[01-13][BDrip][简繁日字幕][1080P][MKV]",
      "BlogThumb": "//static.gmgard.us/Images/thumbs/72083202026174019.jpg",
      "BlogVisit": 6128,
      "PostCount": 21,
      "Author": "[轮回独断] 漫游火焰",
      "BlogDate": "2017-10-20T20:26:18.637"
    },
    {
      "BlogUrl": "/gm85547",
      "Deleted": true,
      "RankDate": "2017-10-22T00:00:00",
      "BlogID": 85547,
      "RankType": 2,
      "Rating": 813,
      "BlogTitle": "(合集)[動畫鉛筆社][モヤモヤ] ソーニャの憂鬱第1、2章",
      "BlogThumb": "//static.gmgard.us/Images/thumbs/20215202115273862.jpg",
      "BlogVisit": 6855,
      "PostCount": 0,
      "Author": "[晓之地平线] sum山葵",
      "BlogDate": "2017-10-21T22:39:15.353"
    },
    {
      "BlogUrl": "/gm85548",
      "Deleted": false,
      "RankDate": "2017-10-21T00:00:00",
      "BlogID": 85548,
      "RankType": 2,
      "Rating": 345,
      "BlogTitle": "[合集][魔穗字幕组]2017年9月作品合集X11(15.97GB)(磁力链)",
      "BlogThumb": "//static.gmgard.us/Images/thumbs/69273202151153862.jpg",
      "BlogVisit": 10999,
      "PostCount": 58,
      "Author": "[eden*] 雨宫优子",
      "BlogDate": "2017-10-21T12:31:41.467"
    },
    {
      "BlogUrl": "/gm85549",
      "Deleted": false,
      "RankDate": "2017-10-21T00:00:00",
      "BlogID": 85549,
      "RankType": 2,
      "Rating": 276,
      "BlogTitle": "[白袍暴君个人汉化][RJ155591][スズネ屋にようこそ (送り萬都)] 悪堕ちた艦~ハジマリノ艦~ (艦隊これくしょん -艦これ-)",
      "BlogThumb": "//static.gmgard.us/Images/thumbs/18953202200503081.jpg",
      "BlogVisit": 8247,
      "PostCount": 53,
      "Author": "[迷影重重] Kerry",
      "BlogDate": "2017-10-21T12:33:47.417"
    },
    {
      "BlogUrl": "/gm85557",
      "Deleted": false,
      "RankDate": "2017-10-21T00:00:00",
      "BlogID": 85557,
      "RankType": 2,
      "Rating": 405,
      "BlogTitle": " [4K掃圖組] [いちこ] ハメともおねえちゃん",
      "BlogThumb": "//static.gmgard.us/Images/thumbs/78621210945416518.jpg",
      "BlogVisit": 13099,
      "PostCount": 137,
      "Author": "[彩虹Project] 跳绳怪",
      "BlogDate": "2017-10-21T12:27:23.667"
    },
    {
      "BlogUrl": "/gm85567",
      "Deleted": false,
      "RankDate": "2017-10-22T00:00:00",
      "BlogID": 85567,
      "RankType": 2,
      "Rating": 1106,
      "BlogTitle": "[MMD]前に投稿した動画をよりエロくした感じのやつ(by acid39)",
      "BlogThumb": "//static.gmgard.us/Images/thumbs/13058211757234175.jpg",
      "BlogVisit": 11370,
      "PostCount": 96,
      "Author": "[权限亦或苦力？] 爱上哆啦的猫",
      "BlogDate": "2017-10-21T22:33:01.497"
    },
    {
      "BlogUrl": "/gm85568",
      "Deleted": false,
      "RankDate": "2017-10-22T00:00:00",
      "BlogID": 85568,
      "RankType": 2,
      "Rating": 614,
      "BlogTitle": "[Kirin个人汉化][ほりとも] アプリでへんたい ハッピーハーピー(コミックアンリアル 2017年10月号 Vol.69) [DL版]",
      "BlogThumb": "//static.gmgard.us/Images/thumbs/18986211938442143.jpg",
      "BlogVisit": 5150,
      "PostCount": 36,
      "Author": "kirin",
      "BlogDate": "2017-10-21T22:33:08.137"
    },
    {
      "BlogUrl": "/gm85574",
      "Deleted": false,
      "RankDate": "2017-10-23T00:00:00",
      "BlogID": 85574,
      "RankType": 2,
      "Rating": 874,
      "BlogTitle": "[无RJ][Mayaka]Girls Army Ver0.68 Free(更新至0.70)",
      "BlogThumb": "//static.gmgard.us/Images/thumbs/17723212156566668.jpg",
      "BlogVisit": 14718,
      "PostCount": 77,
      "Author": "茄子自走炮",
      "BlogDate": "2017-10-22T20:21:00.38"
    },
    {
      "BlogUrl": "/gm85579",
      "Deleted": false,
      "RankDate": "2017-10-22T00:00:00",
      "BlogID": 85579,
      "RankType": 2,
      "Rating": 550,
      "BlogTitle": "[無邪気無修宇宙分組][うまくち醤油] 恋欲キューピッド (COMIC快楽天 2017年8月号) [MJK-17-Z755][無修正]",
      "BlogThumb": "//static.gmgard.us/Images/thumbs/6122220142244950.jpg",
      "BlogVisit": 6773,
      "PostCount": 40,
      "Author": "[神经病，凡是女人] x_single_",
      "BlogDate": "2017-10-22T01:42:25.057"
    },
    {
      "BlogUrl": "/gm85580",
      "Deleted": false,
      "RankDate": "2017-10-22T00:00:00",
      "BlogID": 85580,
      "RankType": 2,
      "Rating": 704,
      "BlogTitle": "[無邪気漢化組 x 就變態][黒ノ樹] 高嶺家の二輪花 prologue (コミック エグゼ 09) [MJK-17-Z757]",
      "BlogThumb": "//static.gmgard.us/Images/thumbs/61432220142406513.jpg",
      "BlogVisit": 9009,
      "PostCount": 76,
      "Author": "[神经病，凡是女人] x_single_",
      "BlogDate": "2017-10-22T01:42:41.043"
    },
    {
      "BlogUrl": "/gm85586",
      "Deleted": false,
      "RankDate": "2017-10-24T00:00:00",
      "BlogID": 85586,
      "RankType": 2,
      "Rating": 839,
      "BlogTitle": "[100827][BISHOP] 学園3~華麗なる悦辱~",
      "BlogThumb": "//static.gmgard.us/Images/thumbs/65569221236228753.jpg",
      "BlogVisit": 8081,
      "PostCount": 78,
      "Author": "[王的力量] 1401567234",
      "BlogDate": "2017-10-23T21:46:13.423"
    },
    {
      "BlogUrl": "/gm85589",
      "Deleted": false,
      "RankDate": "2017-10-23T00:00:00",
      "BlogID": 85589,
      "RankType": 2,
      "Rating": 1126,
      "BlogTitle": "[MMD]ELECT Racing Maho Nishizumi(by J&J)",
      "BlogThumb": "//static.gmgard.us/Images/thumbs/10461221406539223.jpg",
      "BlogVisit": 10695,
      "PostCount": 93,
      "Author": "[权限亦或苦力？] 爱上哆啦的猫",
      "BlogDate": "2017-10-22T20:21:52.52"
    },
    {
      "BlogUrl": "/gm85591",
      "Deleted": false,
      "RankDate": "2017-10-23T00:00:00",
      "BlogID": 85591,
      "RankType": 2,
      "Rating": 758,
      "BlogTitle": "[RJ210169][MiMiA Cute] フタふたっ(2)完遂女子化計画 动画版",
      "BlogThumb": "//static.gmgard.us/Images/thumbs/15330221939188909.jpg",
      "BlogVisit": 11367,
      "PostCount": 68,
      "Author": "[资本的力量] 绅士の触手",
      "BlogDate": "2017-10-22T20:25:32.287"
    },
    {
      "BlogUrl": "/gm85597",
      "Deleted": false,
      "RankDate": "2017-10-23T00:00:00",
      "BlogID": 85597,
      "RankType": 2,
      "Rating": 1056,
      "BlogTitle": "[脸肿汉化组](例大祭10) [のっつぉGT (たいし)] オジョウの奇妙な冒険 (東方Project、ジョジョの奇妙な冒険)",
      "BlogThumb": "http://ww4.sinaimg.cn/large/0060lm7Tly1fkrb7b22l9j30zk1e5gzr.jpg",
      "BlogVisit": 7893,
      "PostCount": 80,
      "Author": "[扶她] F酱",
      "BlogDate": "2017-10-22T20:32:49.13"
    },
    {
      "BlogUrl": "/gm85599",
      "Deleted": false,
      "RankDate": "2017-10-24T00:00:00",
      "BlogID": 85599,
      "RankType": 2,
      "Rating": 1547,
      "BlogTitle": "(成年コミック・雑誌) COMIC LO 10月号増刊 永遠娘 Vol.3",
      "BlogThumb": "//static.gmgard.us/Images/thumbs/42398222201458016.jpg",
      "BlogVisit": 9996,
      "PostCount": 115,
      "Author": "2574942327",
      "BlogDate": "2017-10-23T20:25:07.913"
    },
    {
      "BlogUrl": "/gm85603",
      "Deleted": false,
      "RankDate": "2017-10-23T00:00:00",
      "BlogID": 85603,
      "RankType": 2,
      "Rating": 541,
      "BlogTitle": "[無修正][無邪気無修宇宙分組][麻樹タツキ] 斜め45度の恋 (COMIC快楽天ビースト 2017年10月号) [MJK-17-Z754]",
      "BlogThumb": "//static.gmgard.us/Images/thumbs/60839230044444110.jpg",
      "BlogVisit": 9264,
      "PostCount": 95,
      "Author": "[神经病，凡是女人] x_single_",
      "BlogDate": "2017-10-23T00:44:44.957"
    },
    {
      "BlogUrl": "/gm85612",
      "Deleted": false,
      "RankDate": "2017-10-24T00:00:00",
      "BlogID": 85612,
      "RankType": 2,
      "Rating": 651,
      "BlogTitle": "[RJ204431][Moontrap] モンしょんぐら vol.2 ~悪魔編~",
      "BlogThumb": "//static.gmgard.us/Images/thumbs/15843231427198641.jpg",
      "BlogVisit": 12345,
      "PostCount": 71,
      "Author": "[lowb] 懼魇",
      "BlogDate": "2017-10-24T00:40:39.927"
    },
    {
      "BlogUrl": "/gm85621",
      "Deleted": false,
      "RankDate": "2017-10-26T00:00:00",
      "BlogID": 85621,
      "RankType": 2,
      "Rating": 454,
      "BlogTitle": "[roomv]SECRET BABES 系列集合X3像素游戏",
      "BlogThumb": "//static.gmgard.us/Images/thumbs/14770232226274667.jpg",
      "BlogVisit": 7801,
      "PostCount": 39,
      "Author": "mobbyca",
      "BlogDate": "2017-10-25T21:27:31.8"
    },
    {
      "BlogUrl": "/gm85624",
      "Deleted": false,
      "RankDate": "2017-10-24T00:00:00",
      "BlogID": 85624,
      "RankType": 2,
      "Rating": 560,
      "BlogTitle": "[無邪気漢化組](C92) [peachpulsar (みら)] ちゅーしてヴァンパイアGirls-シスターズパーティー [MJK-17-T759]",
      "BlogThumb": "//static.gmgard.us/Images/thumbs/99853240028140106.jpg",
      "BlogVisit": 5600,
      "PostCount": 40,
      "Author": "[神经病，凡是女人] x_single_",
      "BlogDate": "2017-10-24T00:28:15.76"
    },
    {
      "BlogUrl": "/gm85625",
      "Deleted": false,
      "RankDate": "2017-10-24T00:00:00",
      "BlogID": 85625,
      "RankType": 2,
      "Rating": 728,
      "BlogTitle": "[最終版][無邪気無修宇宙分組][ホムンクルス] 恋ひ結び奇譚 (COMlC 快楽天 2017年11月号) [MJK-17-Z758][無修正]",
      "BlogThumb": "//static.gmgard.us/Images/thumbs/59481240031443100.jpg",
      "BlogVisit": 6963,
      "PostCount": 82,
      "Author": "[神经病，凡是女人] x_single_",
      "BlogDate": "2017-10-24T00:31:44.747"
    },
    {
      "BlogUrl": "/gm85631",
      "Deleted": false,
      "RankDate": "2017-10-25T00:00:00",
      "BlogID": 85631,
      "RankType": 2,
      "Rating": 230,
      "BlogTitle": "[CE家族社] (サンクリ2017 Autumn) [ヒツジ企画 (むねしろ)] ネロイキ!! (Fate/Grand Order)",
      "BlogThumb": "//static.gmgard.us/Images/thumbs/1441241903562933.jpg",
      "BlogVisit": 7753,
      "PostCount": 115,
      "Author": "whotyour",
      "BlogDate": "2017-10-25T14:58:42.767"
    },
    {
      "BlogUrl": "/gm85633",
      "Deleted": false,
      "RankDate": "2017-10-25T00:00:00",
      "BlogID": 85633,
      "RankType": 2,
      "Rating": 1651,
      "BlogTitle": "[无毒汉化组][とっとこMたろう (MだSたろう] Strength and II (BLACK★ROCK SHOOTER)",
      "BlogThumb": "//static.gmgard.us/Images/thumbs/18916242004326371.jpg",
      "BlogVisit": 10411,
      "PostCount": 153,
      "Author": "[德国骨科] 黑杰克6",
      "BlogDate": "2017-10-25T00:44:26.737"
    },
    {
      "BlogUrl": "/gm85634",
      "Deleted": true,
      "RankDate": "2017-10-25T00:00:00",
      "BlogID": 85634,
      "RankType": 2,
      "Rating": 815,
      "BlogTitle": "(合集)(週刊☆海通信ブロク)[なまもななせ] 近期及过往作品不完全补完(部分差分共十三部)(严禁任何转载)",
      "BlogThumb": "//static.gmgard.us/Images/thumbs/12143242058392682.jpg",
      "BlogVisit": 11191,
      "PostCount": 0,
      "Author": "御子の忍び",
      "BlogDate": "2017-10-24T20:58:39.44"
    },
    {
      "BlogUrl": "/gm85635",
      "Deleted": false,
      "RankDate": "2017-10-25T00:00:00",
      "BlogID": 85635,
      "RankType": 2,
      "Rating": 200,
      "BlogTitle": "[兔司姬漢化組](C90) [LockerRoom (100円ロッカー)] フォックス (オリジナル)",
      "BlogThumb": "//static.gmgard.us/Images/thumbs/11490242107238307.jpg",
      "BlogVisit": 5679,
      "PostCount": 58,
      "Author": "[克苏鲁机械] 天下布武喵信长",
      "BlogDate": "2017-10-25T14:58:49.377"
    },
    {
      "BlogUrl": "/gm85638",
      "Deleted": false,
      "RankDate": "2017-10-26T00:00:00",
      "BlogID": 85638,
      "RankType": 2,
      "Rating": 770,
      "BlogTitle": "[朔夜汉化](C92) [極彩色 (彩社長)] 高波、とっても乱れちゃうかもっ!?ですっ! (艦隊これくしょん -艦これ-)",
      "BlogThumb": "//static.gmgard.us/Images/thumbs/8025242241130345.jpg",
      "BlogVisit": 5266,
      "PostCount": 55,
      "Author": "[德国骨科] 黑杰克6",
      "BlogDate": "2017-10-25T20:42:29.05"
    },
    {
      "BlogUrl": "/gm85641",
      "Deleted": false,
      "RankDate": "2017-10-26T00:00:00",
      "BlogID": 85641,
      "RankType": 2,
      "Rating": 1329,
      "BlogTitle": "[RJ211182][ダブルデック製作所] KILL'EM ALL!",
      "BlogThumb": "//static.gmgard.us/Images/thumbs/58622242350037528.jpg",
      "BlogVisit": 9427,
      "PostCount": 153,
      "Author": "[欧洲人] hermetic",
      "BlogDate": "2017-10-25T21:51:41.66"
    },
    {
      "BlogUrl": "/gm85642",
      "Deleted": false,
      "RankDate": "2017-10-25T00:00:00",
      "BlogID": 85642,
      "RankType": 2,
      "Rating": 960,
      "BlogTitle": "[無邪気無修宇宙分組][きょくちょ] ツンデレ彼女を縛ってみた!(COMIC BAVEL 2017年10月号) [MJK-17-Z761]",
      "BlogThumb": "//static.gmgard.us/Images/thumbs/9287250030000338.jpg",
      "BlogVisit": 9130,
      "PostCount": 72,
      "Author": "[神经病，凡是女人] x_single_",
      "BlogDate": "2017-10-25T00:30:00.41"
    },
    {
      "BlogUrl": "/gm85649",
      "Deleted": false,
      "RankDate": "2017-10-26T00:00:00",
      "BlogID": 85649,
      "RankType": 2,
      "Rating": 425,
      "BlogTitle": "[無邪気漢化組](C92) [チデヂ (オヤヂ)] ボクってやっぱり犯されてる姿もカワイイですね (アイドルマスター シンデレラガールズ) [MJK-17-T760]",
      "BlogThumb": "//static.gmgard.us/Images/thumbs/23934260035127214.jpg",
      "BlogVisit": 7657,
      "PostCount": 57,
      "Author": "[神经病，凡是女人] x_single_",
      "BlogDate": "2017-10-26T00:35:13.503"
    },
    {
      "BlogUrl": "/gm85650",
      "Deleted": false,
      "RankDate": "2017-10-26T00:00:00",
      "BlogID": 85650,
      "RankType": 2,
      "Rating": 955,
      "BlogTitle": "科学上网工具  赛风3最新版",
      "BlogThumb": "//static.gmgard.us/Images/thumbs/5182261126350807.jpg",
      "BlogVisit": 21498,
      "PostCount": 290,
      "Author": "[Blessing Software] 云姬",
      "BlogDate": "2017-10-26T11:26:35.127"
    },
    {
      "BlogUrl": "/gm85653",
      "Deleted": false,
      "RankDate": "2017-10-27T00:00:00",
      "BlogID": 85653,
      "RankType": 2,
      "Rating": 1503,
      "BlogTitle": "[屏幕髒了漢化] [みちきんぐ] 姉体験女学寮 3 (COMIC クアンスリウム 2017年11月号) [Digital]",
      "BlogThumb": "//static.gmgard.us/Images/thumbs/81796261414237214.jpg",
      "BlogVisit": 12572,
      "PostCount": 81,
      "Author": "绒布球",
      "BlogDate": "2017-10-26T22:11:24.55"
    },
    {
      "BlogUrl": "/gm85656",
      "Deleted": false,
      "RankDate": "2017-10-27T00:00:00",
      "BlogID": 85656,
      "RankType": 2,
      "Rating": 1245,
      "BlogTitle": "(合集)[紫英字幕组&VCB-Studio]女武神驱动/VALKYRIE DRIVE -MERMAID[全12话+SP6话][BDrip][BIG5][720P][MP4]",
      "BlogThumb": "//static.gmgard.us/Images/thumbs/11199261601041901.jpg",
      "BlogVisit": 13987,
      "PostCount": 75,
      "Author": "[大友] 超恋爱幻想",
      "BlogDate": "2017-10-26T22:12:12.003"
    },
    {
      "BlogUrl": "/gm85661",
      "Deleted": false,
      "RankDate": "2017-10-27T00:00:00",
      "BlogID": 85661,
      "RankType": 2,
      "Rating": 443,
      "BlogTitle": "(合集)[未知字幕组]健全机斗士/健全ロボ ダイミダラー[全12话+SP6话+CM等][BDrip][GB][720P][MP4]",
      "BlogThumb": "//static.gmgard.us/Images/thumbs/13658262204279245.jpg",
      "BlogVisit": 7144,
      "PostCount": 30,
      "Author": "[大友] 超恋爱幻想",
      "BlogDate": "2017-10-26T22:12:21.363"
    },
    {
      "BlogUrl": "/gm85662",
      "Deleted": false,
      "RankDate": "2017-10-27T00:00:00",
      "BlogID": 85662,
      "RankType": 2,
      "Rating": 2291,
      "BlogTitle": "(合集)[澄空学园字幕组]大小姐×执事!/管家后宫学园/れでぃ×ばと!(Ladies versus Butlers!)[全12话+SP6话+NCOPED][BDrip][BIG5][720P][MP4]",
      "BlogThumb": "//static.gmgard.us/Images/thumbs/13684262216552838.jpg",
      "BlogVisit": 21267,
      "PostCount": 206,
      "Author": "[大友] 超恋爱幻想",
      "BlogDate": "2017-10-26T22:20:33.317"
    },
    {
      "BlogUrl": "/gm85668",
      "Deleted": false,
      "RankDate": "2017-10-29T00:00:00",
      "BlogID": 85668,
      "RankType": 2,
      "Rating": 1597,
      "BlogTitle": "(合集)[小虎个人字幕]恶魔高中D×D BorN特典[全6话][BDrip][GB][720P][MP4]",
      "BlogThumb": "//static.gmgard.us/Images/thumbs/3292262322150807.jpg",
      "BlogVisit": 12261,
      "PostCount": 102,
      "Author": "[大友] 超恋爱幻想",
      "BlogDate": "2017-10-27T20:34:45.457"
    },
    {
      "BlogUrl": "/gm85668",
      "Deleted": false,
      "RankDate": "2017-10-28T00:00:00",
      "BlogID": 85668,
      "RankType": 2,
      "Rating": 1452,
      "BlogTitle": "(合集)[小虎个人字幕]恶魔高中D×D BorN特典[全6话][BDrip][GB][720P][MP4]",
      "BlogThumb": "//static.gmgard.us/Images/thumbs/3292262322150807.jpg",
      "BlogVisit": 12261,
      "PostCount": 102,
      "Author": "[大友] 超恋爱幻想",
      "BlogDate": "2017-10-27T20:34:45.457"
    },
    {
      "BlogUrl": "/gm85669",
      "Deleted": false,
      "RankDate": "2017-10-27T00:00:00",
      "BlogID": 85669,
      "RankType": 2,
      "Rating": 735,
      "BlogTitle": "[無邪気無修宇宙分組][れぐでく] フィクションの中ならば (COMIC快楽天ビースト 2017年10月号) [MJK-17-Z762]",
      "BlogThumb": "//static.gmgard.us/Images/thumbs/92777270043046120.jpg",
      "BlogVisit": 6502,
      "PostCount": 55,
      "Author": "[神经病，凡是女人] x_single_",
      "BlogDate": "2017-10-27T00:43:05.173"
    },
    {
      "BlogUrl": "/gm85682",
      "Deleted": false,
      "RankDate": "2017-10-29T00:00:00",
      "BlogID": 85682,
      "RankType": 2,
      "Rating": 3734,
      "BlogTitle": "[提取动画][RJ207058][@OZ]古書堂奇譚 鷺沢無情",
      "BlogThumb": "//static.gmgard.us/Images/thumbs/68962271455370651.jpg",
      "BlogVisit": 21702,
      "PostCount": 230,
      "Author": "[非洲人] Wauchi",
      "BlogDate": "2017-10-27T20:10:36.737"
    },
    {
      "BlogUrl": "/gm85682",
      "Deleted": false,
      "RankDate": "2017-10-28T00:00:00",
      "BlogID": 85682,
      "RankType": 2,
      "Rating": 3439,
      "BlogTitle": "[提取动画][RJ207058][@OZ]古書堂奇譚 鷺沢無情",
      "BlogThumb": "//static.gmgard.us/Images/thumbs/68962271455370651.jpg",
      "BlogVisit": 21702,
      "PostCount": 230,
      "Author": "[非洲人] Wauchi",
      "BlogDate": "2017-10-27T20:10:36.737"
    },
    {
      "BlogUrl": "/gm85695",
      "Deleted": false,
      "RankDate": "2017-10-29T00:00:00",
      "BlogID": 85695,
      "RankType": 2,
      "Rating": 1140,
      "BlogTitle": "[171027][ピンクパイナップル] は~とふるママン THE ANIMATION(度娘)",
      "BlogThumb": "//static.gmgard.us/Images/thumbs/32666271951000963.jpg",
      "BlogVisit": 14097,
      "PostCount": 92,
      "Author": "[恶魔之妹] 拉媞珐·芙尔兰札",
      "BlogDate": "2017-10-27T19:51:00.127"
    },
    {
      "BlogUrl": "/gm85699",
      "Deleted": false,
      "RankDate": "2017-10-28T00:00:00",
      "BlogID": 85699,
      "RankType": 2,
      "Rating": 758,
      "BlogTitle": "[171027][ショーテン] 学園侵触 ×× of the Dead 下巻(度娘)",
      "BlogThumb": "//static.gmgard.us/Images/thumbs/10022272053468463.jpg",
      "BlogVisit": 9638,
      "PostCount": 52,
      "Author": "[恶魔之妹] 拉媞珐·芙尔兰札",
      "BlogDate": "2017-10-27T20:53:46.893"
    },
    {
      "BlogUrl": "/gm85710",
      "Deleted": false,
      "RankDate": "2017-10-28T00:00:00",
      "BlogID": 85710,
      "RankType": 2,
      "Rating": 675,
      "BlogTitle": "[171027][PoRO] 転生剣奴の子作り闘技場(ハーレムコロッセオ)「ケモ耳ちっぱい・ライティウス ~ケダモノ迫るマイクロボディ",
      "BlogThumb": "//static.gmgard.us/Images/thumbs/66232280456178620.jpg",
      "BlogVisit": 14798,
      "PostCount": 91,
      "Author": "[萝莉] 制杖小春",
      "BlogDate": "2017-10-28T04:56:17.987"
    },
    {
      "BlogUrl": "/gm85710",
      "Deleted": false,
      "RankDate": "2017-10-29T00:00:00",
      "BlogID": 85710,
      "RankType": 2,
      "Rating": 1038,
      "BlogTitle": "[171027][PoRO] 転生剣奴の子作り闘技場(ハーレムコロッセオ)「ケモ耳ちっぱい・ライティウス ~ケダモノ迫るマイクロボディ",
      "BlogThumb": "//static.gmgard.us/Images/thumbs/66232280456178620.jpg",
      "BlogVisit": 14798,
      "PostCount": 91,
      "Author": "[萝莉] 制杖小春",
      "BlogDate": "2017-10-28T04:56:17.987"
    },
    {
      "BlogUrl": "/gm85728",
      "Deleted": false,
      "RankDate": "2017-10-29T00:00:00",
      "BlogID": 85728,
      "RankType": 2,
      "Rating": 1598,
      "BlogTitle": "[RJ211497][リフル]姪っこのふくらみ ~いつもの中出しごっこ~",
      "BlogThumb": "//static.gmgard.us/Images/thumbs/89481291410459610.jpg",
      "BlogVisit": 25550,
      "PostCount": 263,
      "Author": "[资本的力量] 爱德",
      "BlogDate": "2017-10-28T16:32:35.097"
    },
    {
      "BlogUrl": "/gm85728",
      "Deleted": false,
      "RankDate": "2017-10-28T00:00:00",
      "BlogID": 85728,
      "RankType": 2,
      "Rating": 560,
      "BlogTitle": "[RJ211497][リフル]姪っこのふくらみ ~いつもの中出しごっこ~",
      "BlogThumb": "//static.gmgard.us/Images/thumbs/89481291410459610.jpg",
      "BlogVisit": 25550,
      "PostCount": 263,
      "Author": "[资本的力量] 爱德",
      "BlogDate": "2017-10-28T16:32:35.097"
    },
    {
      "BlogUrl": "/gm85745",
      "Deleted": false,
      "RankDate": "2017-10-30T00:00:00",
      "BlogID": 85745,
      "RankType": 2,
      "Rating": 753,
      "BlogTitle": "[RJ203736][そうざいそふと] あるけも~ケモミミアルケミスト~ ",
      "BlogThumb": "//static.gmgard.us/Images/thumbs/21356291059146953.jpg",
      "BlogVisit": 7836,
      "PostCount": 55,
      "Author": "[轮回独断] 内藤MOE",
      "BlogDate": "2017-10-29T14:50:04.773"
    },
    {
      "BlogUrl": "/gm85746",
      "Deleted": false,
      "RankDate": "2017-10-30T00:00:00",
      "BlogID": 85746,
      "RankType": 2,
      "Rating": 780,
      "BlogTitle": "[黑锅汉化组] (C92) [緊急発進 (コアヤアコ)] ママママ (Fate/Grand Order)",
      "BlogThumb": "//static.gmgard.us/Images/thumbs/10327291528015235.jpg",
      "BlogVisit": 7991,
      "PostCount": 59,
      "Author": "whotyour",
      "BlogDate": "2017-10-29T18:26:36.257"
    },
    {
      "BlogUrl": "/gm85750",
      "Deleted": false,
      "RankDate": "2017-10-30T00:00:00",
      "BlogID": 85750,
      "RankType": 2,
      "Rating": 1987,
      "BlogTitle": "[MEGA巨莖怪漢化] (C92) [焼肉食べたい (でらうえあ)] ジャンヌオルタちゃんの泥酔聖杯 (Fate/Grand Order)",
      "BlogThumb": "//static.gmgard.us/Images/thumbs/13090291903409922.jpg",
      "BlogVisit": 19927,
      "PostCount": 234,
      "Author": "whotyour",
      "BlogDate": "2017-10-29T19:25:21.257"
    },
    {
      "BlogUrl": "/gm85755",
      "Deleted": false,
      "RankDate": "2017-10-31T00:00:00",
      "BlogID": 85755,
      "RankType": 2,
      "Rating": 1554,
      "BlogTitle": "[兔司姬漢化組](C92) [LockerRoom (100円ロッカー)] フォックス弐 (オリジナル)",
      "BlogThumb": "//static.gmgard.us/Images/thumbs/11460292214564922.jpg",
      "BlogVisit": 12229,
      "PostCount": 167,
      "Author": "[克苏鲁机械] 天下布武喵信长",
      "BlogDate": "2017-10-30T17:53:24.18"
    },
    {
      "BlogUrl": "/gm85756",
      "Deleted": false,
      "RankDate": "2017-10-31T00:00:00",
      "BlogID": 85756,
      "RankType": 2,
      "Rating": 790,
      "BlogTitle": "[171027][HARUKAZE]ノラと皇女と野良猫ハート2 -Nora,Princess,and Crying Cat.-",
      "BlogThumb": "//static.gmgard.us/Images/thumbs/17330292217067109.jpg",
      "BlogVisit": 9280,
      "PostCount": 69,
      "Author": "[七曜的大法师] 里世界的散落君",
      "BlogDate": "2017-10-30T17:59:54.523"
    },
    {
      "BlogUrl": "/gm85764",
      "Deleted": false,
      "RankDate": "2017-10-30T00:00:00",
      "BlogID": 85764,
      "RankType": 2,
      "Rating": 890,
      "BlogTitle": "[無邪気無修宇宙分組][サカガキ] マキリさんの不思議なお店 (COMIC失楽天 2017年10月号) [MJK-17-Z770][無修正]",
      "BlogThumb": "//static.gmgard.us/Images/thumbs/2004292254421641.jpg",
      "BlogVisit": 9193,
      "PostCount": 51,
      "Author": "[神经病，凡是女人] x_single_",
      "BlogDate": "2017-10-29T22:54:42.697"
    },
    {
      "BlogUrl": "/gm85767",
      "Deleted": false,
      "RankDate": "2017-10-30T00:00:00",
      "BlogID": 85767,
      "RankType": 2,
      "Rating": 1426,
      "BlogTitle": "[無邪気無修宇宙分組][しおこんぶ] Is there a witch? (COMIC BAVEL 2017年11月号) [MJK-17-Z764][無修正]",
      "BlogThumb": "//static.gmgard.us/Images/thumbs/92939292258149297.jpg",
      "BlogVisit": 14884,
      "PostCount": 123,
      "Author": "[神经病，凡是女人] x_single_",
      "BlogDate": "2017-10-29T22:58:15.617"
    },
    {
      "BlogUrl": "/gm85772",
      "Deleted": false,
      "RankDate": "2017-10-31T00:00:00",
      "BlogID": 85772,
      "RankType": 2,
      "Rating": 851,
      "BlogTitle": "[171027] [seal-tutu] 異世界風俗始めました!? ~転生したらハーレム性活が待ってました~",
      "BlogThumb": "//static.gmgard.us/Images/thumbs/17427301555374146.jpg",
      "BlogVisit": 9864,
      "PostCount": 93,
      "Author": "[七曜的大法师] 里世界的散落君",
      "BlogDate": "2017-10-30T19:48:43.917"
    },
    {
      "BlogUrl": "/gm85783",
      "Deleted": false,
      "RankDate": "2017-10-31T00:00:00",
      "BlogID": 85783,
      "RankType": 2,
      "Rating": 1019,
      "BlogTitle": "[空気系☆漢化](COMIC1☆12) [ディオゲネスクラブ (灰川ヘムレン)] 高貴なる女騎士様 (ワルキューレロマンツェ)",
      "BlogThumb": "//static.gmgard.us/Images/thumbs/1238302141587427.jpg",
      "BlogVisit": 9418,
      "PostCount": 91,
      "Author": "[原谅她] 長門有希酱",
      "BlogDate": "2017-10-30T21:43:08.023"
    },
    {
      "BlogUrl": "/gm85793",
      "Deleted": false,
      "RankDate": "2017-10-31T00:00:00",
      "BlogID": 85793,
      "RankType": 2,
      "Rating": 817,
      "BlogTitle": "[150828] [SYOKU] ×× of the Dead ",
      "BlogThumb": "//static.gmgard.us/Images/thumbs/20557302315038365.jpg",
      "BlogVisit": 11485,
      "PostCount": 81,
      "Author": "灰灭",
      "BlogDate": "2017-10-30T23:15:04.757"
    }
  ],
  "WeeklyRankings": [
    {
      "BlogUrl": "/gm84922",
      "Deleted": false,
      "RankDate": "2017-10-01T00:00:00",
      "BlogID": 84922,
      "RankType": 3,
      "Rating": 3009,
      "BlogTitle": "[全网首发][魔改无修正版][哈尼喵汉化组x爱丽丝汉化组][040827][ALICESOFT]RanceVI-ゼス崩壊-",
      "BlogThumb": "//static.gmgard.us/Images/thumbs/17880242012436986.jpg",
      "BlogVisit": 14366,
      "PostCount": 160,
      "Author": "乱入杂草",
      "BlogDate": "2017-09-25T17:21:49.927"
    },
    {
      "BlogUrl": "/gm84937",
      "Deleted": false,
      "RankDate": "2017-10-01T00:00:00",
      "BlogID": 84937,
      "RankType": 3,
      "Rating": 2565,
      "BlogTitle": "[夜桜字幕组][RJ193576][survive]母子相姦ゲーム~母を孕ませるまで種付けする温泉旅館~ 第1話",
      "BlogThumb": "//static.gmgard.us/Images/thumbs/11428252033318479.jpg",
      "BlogVisit": 13557,
      "PostCount": 148,
      "Author": "御坂美琴°",
      "BlogDate": "2017-09-26T19:27:50.257"
    },
    {
      "BlogUrl": "/gm84981",
      "Deleted": false,
      "RankDate": "2017-10-01T00:00:00",
      "BlogID": 84981,
      "RankType": 3,
      "Rating": 2911,
      "BlogTitle": "[風的工房] [おおとりりゅうじ] 時間停止Now! ",
      "BlogThumb": "//static.gmgard.us/Images/thumbs/29788272327085147.jpg",
      "BlogVisit": 13916,
      "PostCount": 192,
      "Author": "[原谅她] 地底人",
      "BlogDate": "2017-09-27T23:27:08.623"
    },
    {
      "BlogUrl": "/gm84999",
      "Deleted": false,
      "RankDate": "2017-10-01T00:00:00",
      "BlogID": 84999,
      "RankType": 3,
      "Rating": 3293,
      "BlogTitle": "[桜都字幕组][ばにぃうぉ~か~]おいでよ!水龍敬ランド #2 下半身のアイドル☆ホーニィセントリー(度娘)",
      "BlogThumb": "//static.gmgard.us/Images/thumbs/65349282341338818.jpg",
      "BlogVisit": 16840,
      "PostCount": 223,
      "Author": "[恶魔之妹] 拉媞珐·芙尔兰札",
      "BlogDate": "2017-09-28T23:41:33.977"
    },
    {
      "BlogUrl": "/gm85002",
      "Deleted": false,
      "RankDate": "2017-10-01T00:00:00",
      "BlogID": 85002,
      "RankType": 3,
      "Rating": 2789,
      "BlogTitle": "[とっとこMたろう (MだSたろう、朝凪、BLADE)] Strength and Ⅱ (BLACK★ROCK SHOOTER)",
      "BlogThumb": "//static.gmgard.us/Images/thumbs/19651290902372110.jpg",
      "BlogVisit": 7663,
      "PostCount": 151,
      "Author": "[王的力量] 在原_七海",
      "BlogDate": "2017-09-30T11:40:29.107"
    },
    {
      "BlogUrl": "/gm85092",
      "Deleted": false,
      "RankDate": "2017-10-08T00:00:00",
      "BlogID": 85092,
      "RankType": 3,
      "Rating": 2524,
      "BlogTitle": "[RJ201547][survive] 夏色乙女 俺と従姉妹と爛れた性交に耽った夏の思い出(モーションコミック版) ",
      "BlogThumb": "//static.gmgard.us/Images/thumbs/43389022021498802.jpg",
      "BlogVisit": 13995,
      "PostCount": 127,
      "Author": "[斑比酱的眷属] 高阪穗乃果",
      "BlogDate": "2017-10-03T01:11:03.973"
    },
    {
      "BlogUrl": "/gm85105",
      "Deleted": true,
      "RankDate": "2017-10-08T00:00:00",
      "BlogID": 85105,
      "RankType": 3,
      "Rating": 2729,
      "BlogTitle": "[gfpa个人汉化][170428][ILLUSION] HoneySelect(ハニーセレクト)+大型资料片DLC《ハニーセレクト ~パーティー~》",
      "BlogThumb": "//static.gmgard.us/Images/thumbs/77366040142175486.jpg",
      "BlogVisit": 26829,
      "PostCount": 0,
      "Author": "大叔来一发吧",
      "BlogDate": "2017-10-04T20:33:58.55"
    },
    {
      "BlogUrl": "/gm85149",
      "Deleted": false,
      "RankDate": "2017-10-08T00:00:00",
      "BlogID": 85149,
      "RankType": 3,
      "Rating": 2415,
      "BlogTitle": "[脸肿字幕组][ピンクパイナップル]ばくあね 弟しぼっちゃうぞ! THE ANIMATION ディレクターズカット版",
      "BlogThumb": "//static.gmgard.us/Images/thumbs/63214041738439875.jpg",
      "BlogVisit": 15442,
      "PostCount": 157,
      "Author": "j瑛里华",
      "BlogDate": "2017-10-04T20:36:25.677"
    },
    {
      "BlogUrl": "/gm85180",
      "Deleted": false,
      "RankDate": "2017-10-08T00:00:00",
      "BlogID": 85180,
      "RankType": 3,
      "Rating": 2349,
      "BlogTitle": "[final個人漢化](C92) [熟成角砂糖 (sugarBt)] ウルトラビーストなんてなかった2 (ポケットモンスター サン･ムーン)",
      "BlogThumb": "//static.gmgard.us/Images/thumbs/10551052116541590.jpg",
      "BlogVisit": 12934,
      "PostCount": 129,
      "Author": "[最远的最近] 老囧",
      "BlogDate": "2017-10-05T21:18:08.8"
    },
    {
      "BlogUrl": "/gm85235",
      "Deleted": false,
      "RankDate": "2017-10-08T00:00:00",
      "BlogID": 85235,
      "RankType": 3,
      "Rating": 3659,
      "BlogTitle": "[桜都字幕组][メリー・ジェーン]キメ恋! 高嶺の華と幼なじみがキマった理由 上巻魔法の薬で恋の成就を(度娘)",
      "BlogThumb": "//static.gmgard.us/Images/thumbs/18158062114547247.jpg",
      "BlogVisit": 17020,
      "PostCount": 278,
      "Author": "[恶魔之妹] 拉媞珐·芙尔兰札",
      "BlogDate": "2017-10-06T21:14:54.773"
    },
    {
      "BlogUrl": "/gm85296",
      "Deleted": false,
      "RankDate": "2017-10-15T00:00:00",
      "BlogID": 85296,
      "RankType": 3,
      "Rating": 2730,
      "BlogTitle": "[闪灵二人组汉化][ありのとわたり] 隣のビッチギャルと純情少年 (COMIC X-EROS #59 )[Digital]",
      "BlogThumb": "//static.gmgard.us/Images/thumbs/57475080055069366.jpg",
      "BlogVisit": 11165,
      "PostCount": 171,
      "Author": "苍穹KID",
      "BlogDate": "2017-10-08T19:41:44.243"
    },
    {
      "BlogUrl": "/gm85320",
      "Deleted": false,
      "RankDate": "2017-10-15T00:00:00",
      "BlogID": 85320,
      "RankType": 3,
      "Rating": 2929,
      "BlogTitle": "[RJ205013] [アトリエわだつみ]チャイナ・インフェルノ Ver.1.0",
      "BlogThumb": "//static.gmgard.us/Images/thumbs/75580082036255557.jpg",
      "BlogVisit": 15897,
      "PostCount": 181,
      "Author": "[lowb] 懼魇",
      "BlogDate": "2017-10-10T00:18:12.713"
    },
    {
      "BlogUrl": "/gm85321",
      "Deleted": false,
      "RankDate": "2017-10-15T00:00:00",
      "BlogID": 85321,
      "RankType": 3,
      "Rating": 2559,
      "BlogTitle": "[桜都字幕组][BOOTLEG]さきゅばみすと・すとーりー ~のんひゅーまあんらいふ~ THE ANIMATION(度娘)",
      "BlogThumb": "//static.gmgard.us/Images/thumbs/20018101929069675.jpg",
      "BlogVisit": 20024,
      "PostCount": 174,
      "Author": "j瑛里华",
      "BlogDate": "2017-10-09T22:04:04.12"
    },
    {
      "BlogUrl": "/gm85353",
      "Deleted": false,
      "RankDate": "2017-10-15T00:00:00",
      "BlogID": 85353,
      "RankType": 3,
      "Rating": 2630,
      "BlogTitle": "[兔司鸡汉化组][雛原えみ] きちんとしなさいっ! (COMlC 快楽天 2017年11月号)",
      "BlogThumb": "//static.gmgard.us/Images/thumbs/19565101812519363.jpg",
      "BlogVisit": 8720,
      "PostCount": 128,
      "Author": "[克苏鲁机械] 天下布武喵信长",
      "BlogDate": "2017-10-10T18:22:13.763"
    },
    {
      "BlogUrl": "/gm85403",
      "Deleted": false,
      "RankDate": "2017-10-15T00:00:00",
      "BlogID": 85403,
      "RankType": 3,
      "Rating": 4283,
      "BlogTitle": "[附ZOD界面汉化补丁][171013][ILLUSION]プレイホーム(PLAY HOME)(购入特典&预约特典附)",
      "BlogThumb": "//static.gmgard.us/Images/thumbs/18040131226453239.jpg",
      "BlogVisit": 16641,
      "PostCount": 474,
      "Author": "[欧洲人] ziz",
      "BlogDate": "2017-10-14T09:52:45.273"
    },
    {
      "BlogUrl": "/gm85448",
      "Deleted": false,
      "RankDate": "2017-10-22T00:00:00",
      "BlogID": 85448,
      "RankType": 3,
      "Rating": 2410,
      "BlogTitle": "[新视界中文版] [ピジャ]  ねぇ、…しよ♥",
      "BlogThumb": "//static.gmgard.us/Images/thumbs/81767151128406395.jpg",
      "BlogVisit": 16077,
      "PostCount": 146,
      "Author": "[彩虹Project] 跳绳怪",
      "BlogDate": "2017-10-15T18:24:08.783"
    },
    {
      "BlogUrl": "/gm85460",
      "Deleted": false,
      "RankDate": "2017-10-22T00:00:00",
      "BlogID": 85460,
      "RankType": 3,
      "Rating": 3199,
      "BlogTitle": "[4K掃圖組] [さいもん] 異世界の魔法使い",
      "BlogThumb": "//static.gmgard.us/Images/thumbs/20883152341186982.jpg",
      "BlogVisit": 15976,
      "PostCount": 181,
      "Author": "[彩虹Project] 跳绳怪",
      "BlogDate": "2017-10-16T16:38:02.74"
    },
    {
      "BlogUrl": "/gm85473",
      "Deleted": false,
      "RankDate": "2017-10-22T00:00:00",
      "BlogID": 85473,
      "RankType": 3,
      "Rating": 2802,
      "BlogTitle": "uTorrent.v2.21-----代替渣雷的小道具",
      "BlogThumb": "//static.gmgard.us/Images/thumbs/72252161019572455.jpg",
      "BlogVisit": 9212,
      "PostCount": 218,
      "Author": "[欧洲人] 黒翼凤尾蝶",
      "BlogDate": "2017-10-17T13:44:26.313"
    },
    {
      "BlogUrl": "/gm85476",
      "Deleted": false,
      "RankDate": "2017-10-22T00:00:00",
      "BlogID": 85476,
      "RankType": 3,
      "Rating": 2293,
      "BlogTitle": "[汉化硬盘版][脸肿汉化组][160527] [Frill] 清楚で真面目な彼女が、最凶ヤリサーに勧誘されたら…?(附全CG存档)",
      "BlogThumb": "//static.gmgard.us/Images/thumbs/66292172206325644.jpg",
      "BlogVisit": 11665,
      "PostCount": 159,
      "Author": "rapt1993",
      "BlogDate": "2017-10-17T22:05:40.627"
    },
    {
      "BlogUrl": "/gm85512",
      "Deleted": false,
      "RankDate": "2017-10-22T00:00:00",
      "BlogID": 85512,
      "RankType": 3,
      "Rating": 2833,
      "BlogTitle": " [无毒汉化组](C92) [USAGIBOSU (くろわ)] DEEP d'ARC FANTASY (Fate/Grand Order)",
      "BlogThumb": "//static.gmgard.us/Images/thumbs/51523190119419111.jpg",
      "BlogVisit": 10372,
      "PostCount": 179,
      "Author": "[好朋友] 绅士的我33",
      "BlogDate": "2017-10-19T11:46:39.747"
    },
    {
      "BlogUrl": "/gm85633",
      "Deleted": false,
      "RankDate": "2017-10-29T00:00:00",
      "BlogID": 85633,
      "RankType": 3,
      "Rating": 3170,
      "BlogTitle": "[无毒汉化组][とっとこMたろう (MだSたろう] Strength and II (BLACK★ROCK SHOOTER)",
      "BlogThumb": "//static.gmgard.us/Images/thumbs/18916242004326371.jpg",
      "BlogVisit": 8086,
      "PostCount": 153,
      "Author": "[德国骨科] 黑杰克6",
      "BlogDate": "2017-10-25T00:44:26.737"
    },
    {
      "BlogUrl": "/gm85650",
      "Deleted": false,
      "RankDate": "2017-10-29T00:00:00",
      "BlogID": 85650,
      "RankType": 3,
      "Rating": 3542,
      "BlogTitle": "科学上网工具  赛风3最新版",
      "BlogThumb": "//static.gmgard.us/Images/thumbs/5182261126350807.jpg",
      "BlogVisit": 11119,
      "PostCount": 290,
      "Author": "[Blessing Software] 云姬",
      "BlogDate": "2017-10-26T11:26:35.127"
    },
    {
      "BlogUrl": "/gm85662",
      "Deleted": false,
      "RankDate": "2017-10-29T00:00:00",
      "BlogID": 85662,
      "RankType": 3,
      "Rating": 2831,
      "BlogTitle": "(合集)[澄空学园字幕组]大小姐×执事!/管家后宫学园/れでぃ×ばと!(Ladies versus Butlers!)[全12话+SP6话+NCOPED][BDrip][BIG5][720P][MP4]",
      "BlogThumb": "//static.gmgard.us/Images/thumbs/13684262216552838.jpg",
      "BlogVisit": 14115,
      "PostCount": 206,
      "Author": "[大友] 超恋爱幻想",
      "BlogDate": "2017-10-26T22:20:33.317"
    },
    {
      "BlogUrl": "/gm85682",
      "Deleted": false,
      "RankDate": "2017-10-29T00:00:00",
      "BlogID": 85682,
      "RankType": 3,
      "Rating": 4224,
      "BlogTitle": "[提取动画][RJ207058][@OZ]古書堂奇譚 鷺沢無情",
      "BlogThumb": "//static.gmgard.us/Images/thumbs/68962271455370651.jpg",
      "BlogVisit": 12330,
      "PostCount": 230,
      "Author": "[非洲人] Wauchi",
      "BlogDate": "2017-10-27T20:10:36.737"
    },
    {
      "BlogUrl": "/gm85728",
      "Deleted": false,
      "RankDate": "2017-10-29T00:00:00",
      "BlogID": 85728,
      "RankType": 3,
      "Rating": 3661,
      "BlogTitle": "[RJ211497][リフル]姪っこのふくらみ ~いつもの中出しごっこ~",
      "BlogThumb": "//static.gmgard.us/Images/thumbs/89481291410459610.jpg",
      "BlogVisit": 12618,
      "PostCount": 263,
      "Author": "[资本的力量] 爱德",
      "BlogDate": "2017-10-28T16:32:35.097"
    }
  ],
  "MonthlyRankings": [
    {
      "BlogUrl": "/gm85035",
      "Deleted": false,
      "RankDate": "2017-10-31T00:00:00",
      "BlogID": 85035,
      "RankType": 4,
      "Rating": 3662,
      "BlogTitle": "[170929] [MONAKO] キミに迫るオトメのレッスン",
      "BlogThumb": "//static.gmgard.us/Images/thumbs/18018302200398859.jpg",
      "BlogVisit": 26205,
      "PostCount": 185,
      "Author": "[德国骨科] 逗得一B",
      "BlogDate": "2017-10-01T12:45:33.567"
    },
    {
      "BlogUrl": "/gm85235",
      "Deleted": false,
      "RankDate": "2017-10-31T00:00:00",
      "BlogID": 85235,
      "RankType": 4,
      "Rating": 4569,
      "BlogTitle": "[桜都字幕组][メリー・ジェーン]キメ恋! 高嶺の華と幼なじみがキマった理由 上巻魔法の薬で恋の成就を(度娘)",
      "BlogThumb": "//static.gmgard.us/Images/thumbs/18158062114547247.jpg",
      "BlogVisit": 32966,
      "PostCount": 278,
      "Author": "[恶魔之妹] 拉媞珐·芙尔兰札",
      "BlogDate": "2017-10-06T21:14:54.773"
    },
    {
      "BlogUrl": "/gm85403",
      "Deleted": false,
      "RankDate": "2017-10-31T00:00:00",
      "BlogID": 85403,
      "RankType": 4,
      "Rating": 5942,
      "BlogTitle": "[附ZOD界面汉化补丁][171013][ILLUSION]プレイホーム(PLAY HOME)(购入特典&预约特典附)",
      "BlogThumb": "//static.gmgard.us/Images/thumbs/18040131226453239.jpg",
      "BlogVisit": 35349,
      "PostCount": 474,
      "Author": "[欧洲人] ziz",
      "BlogDate": "2017-10-14T09:52:45.273"
    },
    {
      "BlogUrl": "/gm85682",
      "Deleted": false,
      "RankDate": "2017-10-31T00:00:00",
      "BlogID": 85682,
      "RankType": 4,
      "Rating": 4564,
      "BlogTitle": "[提取动画][RJ207058][@OZ]古書堂奇譚 鷺沢無情",
      "BlogThumb": "//static.gmgard.us/Images/thumbs/68962271455370651.jpg",
      "BlogVisit": 14331,
      "PostCount": 230,
      "Author": "[非洲人] Wauchi",
      "BlogDate": "2017-10-27T20:10:36.737"
    },
    {
      "BlogUrl": "/gm85728",
      "Deleted": false,
      "RankDate": "2017-10-31T00:00:00",
      "BlogID": 85728,
      "RankType": 4,
      "Rating": 4137,
      "BlogTitle": "[RJ211497][リフル]姪っこのふくらみ ~いつもの中出しごっこ~",
      "BlogThumb": "//static.gmgard.us/Images/thumbs/89481291410459610.jpg",
      "BlogVisit": 15598,
      "PostCount": 263,
      "Author": "[资本的力量] 爱德",
      "BlogDate": "2017-10-28T16:32:35.097"
    }
  ]
}